{
    "100": "NoDur",
    "101": "NoDur",
    "102": "NoDur",
    "103": "NoDur",
    "104": "NoDur",
    "105": "NoDur",
    "106": "NoDur",
    "107": "NoDur",
    "108": "NoDur",
    "109": "NoDur",
    "110": "NoDur",
    "111": "NoDur",
    "112": "NoDur",
    "113": "NoDur",
    "114": "NoDur",
    "115": "NoDur",
    "116": "NoDur",
    "117": "NoDur",
    "118": "NoDur",
    "119": "NoDur",
    "120": "NoDur",
    "121": "NoDur",
    "122": "NoDur",
    "123": "NoDur",
    "124": "NoDur",
    "125": "NoDur",
    "126": "NoDur",
    "127": "NoDur",
    "128": "NoDur",
    "129": "NoDur",
    "130": "NoDur",
    "131": "NoDur",
    "132": "NoDur",
    "133": "NoDur",
    "134": "NoDur",
    "135": "NoDur",
    "136": "NoDur",
    "137": "NoDur",
    "138": "NoDur",
    "139": "NoDur",
    "140": "NoDur",
    "141": "NoDur",
    "142": "NoDur",
    "143": "NoDur",
    "144": "NoDur",
    "145": "NoDur",
    "146": "NoDur",
    "147": "NoDur",
    "148": "NoDur",
    "149": "NoDur",
    "150": "NoDur",
    "151": "NoDur",
    "152": "NoDur",
    "153": "NoDur",
    "154": "NoDur",
    "155": "NoDur",
    "156": "NoDur",
    "157": "NoDur",
    "158": "NoDur",
    "159": "NoDur",
    "160": "NoDur",
    "161": "NoDur",
    "162": "NoDur",
    "163": "NoDur",
    "164": "NoDur",
    "165": "NoDur",
    "166": "NoDur",
    "167": "NoDur",
    "168": "NoDur",
    "169": "NoDur",
    "170": "NoDur",
    "171": "NoDur",
    "172": "NoDur",
    "173": "NoDur",
    "174": "NoDur",
    "175": "NoDur",
    "176": "NoDur",
    "177": "NoDur",
    "178": "NoDur",
    "179": "NoDur",
    "180": "NoDur",
    "181": "NoDur",
    "182": "NoDur",
    "183": "NoDur",
    "184": "NoDur",
    "185": "NoDur",
    "186": "NoDur",
    "187": "NoDur",
    "188": "NoDur",
    "189": "NoDur",
    "190": "NoDur",
    "191": "NoDur",
    "192": "NoDur",
    "193": "NoDur",
    "194": "NoDur",
    "195": "NoDur",
    "196": "NoDur",
    "197": "NoDur",
    "198": "NoDur",
    "199": "NoDur",
    "200": "NoDur",
    "201": "NoDur",
    "202": "NoDur",
    "203": "NoDur",
    "204": "NoDur",
    "205": "NoDur",
    "206": "NoDur",
    "207": "NoDur",
    "208": "NoDur",
    "209": "NoDur",
    "210": "NoDur",
    "211": "NoDur",
    "212": "NoDur",
    "213": "NoDur",
    "214": "NoDur",
    "215": "NoDur",
    "216": "NoDur",
    "217": "NoDur",
    "218": "NoDur",
    "219": "NoDur",
    "220": "NoDur",
    "221": "NoDur",
    "222": "NoDur",
    "223": "NoDur",
    "224": "NoDur",
    "225": "NoDur",
    "226": "NoDur",
    "227": "NoDur",
    "228": "NoDur",
    "229": "NoDur",
    "230": "NoDur",
    "231": "NoDur",
    "232": "NoDur",
    "233": "NoDur",
    "234": "NoDur",
    "235": "NoDur",
    "236": "NoDur",
    "237": "NoDur",
    "238": "NoDur",
    "239": "NoDur",
    "240": "NoDur",
    "241": "NoDur",
    "242": "NoDur",
    "243": "NoDur",
    "244": "NoDur",
    "245": "NoDur",
    "246": "NoDur",
    "247": "NoDur",
    "248": "NoDur",
    "249": "NoDur",
    "250": "NoDur",
    "251": "NoDur",
    "252": "NoDur",
    "253": "NoDur",
    "254": "NoDur",
    "255": "NoDur",
    "256": "NoDur",
    "257": "NoDur",
    "258": "NoDur",
    "259": "NoDur",
    "260": "NoDur",
    "261": "NoDur",
    "262": "NoDur",
    "263": "NoDur",
    "264": "NoDur",
    "265": "NoDur",
    "266": "NoDur",
    "267": "NoDur",
    "268": "NoDur",
    "269": "NoDur",
    "270": "NoDur",
    "271": "NoDur",
    "272": "NoDur",
    "273": "NoDur",
    "274": "NoDur",
    "275": "NoDur",
    "276": "NoDur",
    "277": "NoDur",
    "278": "NoDur",
    "279": "NoDur",
    "280": "NoDur",
    "281": "NoDur",
    "282": "NoDur",
    "283": "NoDur",
    "284": "NoDur",
    "285": "NoDur",
    "286": "NoDur",
    "287": "NoDur",
    "288": "NoDur",
    "289": "NoDur",
    "290": "NoDur",
    "291": "NoDur",
    "292": "NoDur",
    "293": "NoDur",
    "294": "NoDur",
    "295": "NoDur",
    "296": "NoDur",
    "297": "NoDur",
    "298": "NoDur",
    "299": "NoDur",
    "300": "NoDur",
    "301": "NoDur",
    "302": "NoDur",
    "303": "NoDur",
    "304": "NoDur",
    "305": "NoDur",
    "306": "NoDur",
    "307": "NoDur",
    "308": "NoDur",
    "309": "NoDur",
    "310": "NoDur",
    "311": "NoDur",
    "312": "NoDur",
    "313": "NoDur",
    "314": "NoDur",
    "315": "NoDur",
    "316": "NoDur",
    "317": "NoDur",
    "318": "NoDur",
    "319": "NoDur",
    "320": "NoDur",
    "321": "NoDur",
    "322": "NoDur",
    "323": "NoDur",
    "324": "NoDur",
    "325": "NoDur",
    "326": "NoDur",
    "327": "NoDur",
    "328": "NoDur",
    "329": "NoDur",
    "330": "NoDur",
    "331": "NoDur",
    "332": "NoDur",
    "333": "NoDur",
    "334": "NoDur",
    "335": "NoDur",
    "336": "NoDur",
    "337": "NoDur",
    "338": "NoDur",
    "339": "NoDur",
    "340": "NoDur",
    "341": "NoDur",
    "342": "NoDur",
    "343": "NoDur",
    "344": "NoDur",
    "345": "NoDur",
    "346": "NoDur",
    "347": "NoDur",
    "348": "NoDur",
    "349": "NoDur",
    "350": "NoDur",
    "351": "NoDur",
    "352": "NoDur",
    "353": "NoDur",
    "354": "NoDur",
    "355": "NoDur",
    "356": "NoDur",
    "357": "NoDur",
    "358": "NoDur",
    "359": "NoDur",
    "360": "NoDur",
    "361": "NoDur",
    "362": "NoDur",
    "363": "NoDur",
    "364": "NoDur",
    "365": "NoDur",
    "366": "NoDur",
    "367": "NoDur",
    "368": "NoDur",
    "369": "NoDur",
    "370": "NoDur",
    "371": "NoDur",
    "372": "NoDur",
    "373": "NoDur",
    "374": "NoDur",
    "375": "NoDur",
    "376": "NoDur",
    "377": "NoDur",
    "378": "NoDur",
    "379": "NoDur",
    "380": "NoDur",
    "381": "NoDur",
    "382": "NoDur",
    "383": "NoDur",
    "384": "NoDur",
    "385": "NoDur",
    "386": "NoDur",
    "387": "NoDur",
    "388": "NoDur",
    "389": "NoDur",
    "390": "NoDur",
    "391": "NoDur",
    "392": "NoDur",
    "393": "NoDur",
    "394": "NoDur",
    "395": "NoDur",
    "396": "NoDur",
    "397": "NoDur",
    "398": "NoDur",
    "399": "NoDur",
    "400": "NoDur",
    "401": "NoDur",
    "402": "NoDur",
    "403": "NoDur",
    "404": "NoDur",
    "405": "NoDur",
    "406": "NoDur",
    "407": "NoDur",
    "408": "NoDur",
    "409": "NoDur",
    "410": "NoDur",
    "411": "NoDur",
    "412": "NoDur",
    "413": "NoDur",
    "414": "NoDur",
    "415": "NoDur",
    "416": "NoDur",
    "417": "NoDur",
    "418": "NoDur",
    "419": "NoDur",
    "420": "NoDur",
    "421": "NoDur",
    "422": "NoDur",
    "423": "NoDur",
    "424": "NoDur",
    "425": "NoDur",
    "426": "NoDur",
    "427": "NoDur",
    "428": "NoDur",
    "429": "NoDur",
    "430": "NoDur",
    "431": "NoDur",
    "432": "NoDur",
    "433": "NoDur",
    "434": "NoDur",
    "435": "NoDur",
    "436": "NoDur",
    "437": "NoDur",
    "438": "NoDur",
    "439": "NoDur",
    "440": "NoDur",
    "441": "NoDur",
    "442": "NoDur",
    "443": "NoDur",
    "444": "NoDur",
    "445": "NoDur",
    "446": "NoDur",
    "447": "NoDur",
    "448": "NoDur",
    "449": "NoDur",
    "450": "NoDur",
    "451": "NoDur",
    "452": "NoDur",
    "453": "NoDur",
    "454": "NoDur",
    "455": "NoDur",
    "456": "NoDur",
    "457": "NoDur",
    "458": "NoDur",
    "459": "NoDur",
    "460": "NoDur",
    "461": "NoDur",
    "462": "NoDur",
    "463": "NoDur",
    "464": "NoDur",
    "465": "NoDur",
    "466": "NoDur",
    "467": "NoDur",
    "468": "NoDur",
    "469": "NoDur",
    "470": "NoDur",
    "471": "NoDur",
    "472": "NoDur",
    "473": "NoDur",
    "474": "NoDur",
    "475": "NoDur",
    "476": "NoDur",
    "477": "NoDur",
    "478": "NoDur",
    "479": "NoDur",
    "480": "NoDur",
    "481": "NoDur",
    "482": "NoDur",
    "483": "NoDur",
    "484": "NoDur",
    "485": "NoDur",
    "486": "NoDur",
    "487": "NoDur",
    "488": "NoDur",
    "489": "NoDur",
    "490": "NoDur",
    "491": "NoDur",
    "492": "NoDur",
    "493": "NoDur",
    "494": "NoDur",
    "495": "NoDur",
    "496": "NoDur",
    "497": "NoDur",
    "498": "NoDur",
    "499": "NoDur",
    "500": "NoDur",
    "501": "NoDur",
    "502": "NoDur",
    "503": "NoDur",
    "504": "NoDur",
    "505": "NoDur",
    "506": "NoDur",
    "507": "NoDur",
    "508": "NoDur",
    "509": "NoDur",
    "510": "NoDur",
    "511": "NoDur",
    "512": "NoDur",
    "513": "NoDur",
    "514": "NoDur",
    "515": "NoDur",
    "516": "NoDur",
    "517": "NoDur",
    "518": "NoDur",
    "519": "NoDur",
    "520": "NoDur",
    "521": "NoDur",
    "522": "NoDur",
    "523": "NoDur",
    "524": "NoDur",
    "525": "NoDur",
    "526": "NoDur",
    "527": "NoDur",
    "528": "NoDur",
    "529": "NoDur",
    "530": "NoDur",
    "531": "NoDur",
    "532": "NoDur",
    "533": "NoDur",
    "534": "NoDur",
    "535": "NoDur",
    "536": "NoDur",
    "537": "NoDur",
    "538": "NoDur",
    "539": "NoDur",
    "540": "NoDur",
    "541": "NoDur",
    "542": "NoDur",
    "543": "NoDur",
    "544": "NoDur",
    "545": "NoDur",
    "546": "NoDur",
    "547": "NoDur",
    "548": "NoDur",
    "549": "NoDur",
    "550": "NoDur",
    "551": "NoDur",
    "552": "NoDur",
    "553": "NoDur",
    "554": "NoDur",
    "555": "NoDur",
    "556": "NoDur",
    "557": "NoDur",
    "558": "NoDur",
    "559": "NoDur",
    "560": "NoDur",
    "561": "NoDur",
    "562": "NoDur",
    "563": "NoDur",
    "564": "NoDur",
    "565": "NoDur",
    "566": "NoDur",
    "567": "NoDur",
    "568": "NoDur",
    "569": "NoDur",
    "570": "NoDur",
    "571": "NoDur",
    "572": "NoDur",
    "573": "NoDur",
    "574": "NoDur",
    "575": "NoDur",
    "576": "NoDur",
    "577": "NoDur",
    "578": "NoDur",
    "579": "NoDur",
    "580": "NoDur",
    "581": "NoDur",
    "582": "NoDur",
    "583": "NoDur",
    "584": "NoDur",
    "585": "NoDur",
    "586": "NoDur",
    "587": "NoDur",
    "588": "NoDur",
    "589": "NoDur",
    "590": "NoDur",
    "591": "NoDur",
    "592": "NoDur",
    "593": "NoDur",
    "594": "NoDur",
    "595": "NoDur",
    "596": "NoDur",
    "597": "NoDur",
    "598": "NoDur",
    "599": "NoDur",
    "600": "NoDur",
    "601": "NoDur",
    "602": "NoDur",
    "603": "NoDur",
    "604": "NoDur",
    "605": "NoDur",
    "606": "NoDur",
    "607": "NoDur",
    "608": "NoDur",
    "609": "NoDur",
    "610": "NoDur",
    "611": "NoDur",
    "612": "NoDur",
    "613": "NoDur",
    "614": "NoDur",
    "615": "NoDur",
    "616": "NoDur",
    "617": "NoDur",
    "618": "NoDur",
    "619": "NoDur",
    "620": "NoDur",
    "621": "NoDur",
    "622": "NoDur",
    "623": "NoDur",
    "624": "NoDur",
    "625": "NoDur",
    "626": "NoDur",
    "627": "NoDur",
    "628": "NoDur",
    "629": "NoDur",
    "630": "NoDur",
    "631": "NoDur",
    "632": "NoDur",
    "633": "NoDur",
    "634": "NoDur",
    "635": "NoDur",
    "636": "NoDur",
    "637": "NoDur",
    "638": "NoDur",
    "639": "NoDur",
    "640": "NoDur",
    "641": "NoDur",
    "642": "NoDur",
    "643": "NoDur",
    "644": "NoDur",
    "645": "NoDur",
    "646": "NoDur",
    "647": "NoDur",
    "648": "NoDur",
    "649": "NoDur",
    "650": "NoDur",
    "651": "NoDur",
    "652": "NoDur",
    "653": "NoDur",
    "654": "NoDur",
    "655": "NoDur",
    "656": "NoDur",
    "657": "NoDur",
    "658": "NoDur",
    "659": "NoDur",
    "660": "NoDur",
    "661": "NoDur",
    "662": "NoDur",
    "663": "NoDur",
    "664": "NoDur",
    "665": "NoDur",
    "666": "NoDur",
    "667": "NoDur",
    "668": "NoDur",
    "669": "NoDur",
    "670": "NoDur",
    "671": "NoDur",
    "672": "NoDur",
    "673": "NoDur",
    "674": "NoDur",
    "675": "NoDur",
    "676": "NoDur",
    "677": "NoDur",
    "678": "NoDur",
    "679": "NoDur",
    "680": "NoDur",
    "681": "NoDur",
    "682": "NoDur",
    "683": "NoDur",
    "684": "NoDur",
    "685": "NoDur",
    "686": "NoDur",
    "687": "NoDur",
    "688": "NoDur",
    "689": "NoDur",
    "690": "NoDur",
    "691": "NoDur",
    "692": "NoDur",
    "693": "NoDur",
    "694": "NoDur",
    "695": "NoDur",
    "696": "NoDur",
    "697": "NoDur",
    "698": "NoDur",
    "699": "NoDur",
    "700": "NoDur",
    "701": "NoDur",
    "702": "NoDur",
    "703": "NoDur",
    "704": "NoDur",
    "705": "NoDur",
    "706": "NoDur",
    "707": "NoDur",
    "708": "NoDur",
    "709": "NoDur",
    "710": "NoDur",
    "711": "NoDur",
    "712": "NoDur",
    "713": "NoDur",
    "714": "NoDur",
    "715": "NoDur",
    "716": "NoDur",
    "717": "NoDur",
    "718": "NoDur",
    "719": "NoDur",
    "720": "NoDur",
    "721": "NoDur",
    "722": "NoDur",
    "723": "NoDur",
    "724": "NoDur",
    "725": "NoDur",
    "726": "NoDur",
    "727": "NoDur",
    "728": "NoDur",
    "729": "NoDur",
    "730": "NoDur",
    "731": "NoDur",
    "732": "NoDur",
    "733": "NoDur",
    "734": "NoDur",
    "735": "NoDur",
    "736": "NoDur",
    "737": "NoDur",
    "738": "NoDur",
    "739": "NoDur",
    "740": "NoDur",
    "741": "NoDur",
    "742": "NoDur",
    "743": "NoDur",
    "744": "NoDur",
    "745": "NoDur",
    "746": "NoDur",
    "747": "NoDur",
    "748": "NoDur",
    "749": "NoDur",
    "750": "NoDur",
    "751": "NoDur",
    "752": "NoDur",
    "753": "NoDur",
    "754": "NoDur",
    "755": "NoDur",
    "756": "NoDur",
    "757": "NoDur",
    "758": "NoDur",
    "759": "NoDur",
    "760": "NoDur",
    "761": "NoDur",
    "762": "NoDur",
    "763": "NoDur",
    "764": "NoDur",
    "765": "NoDur",
    "766": "NoDur",
    "767": "NoDur",
    "768": "NoDur",
    "769": "NoDur",
    "770": "NoDur",
    "771": "NoDur",
    "772": "NoDur",
    "773": "NoDur",
    "774": "NoDur",
    "775": "NoDur",
    "776": "NoDur",
    "777": "NoDur",
    "778": "NoDur",
    "779": "NoDur",
    "780": "NoDur",
    "781": "NoDur",
    "782": "NoDur",
    "783": "NoDur",
    "784": "NoDur",
    "785": "NoDur",
    "786": "NoDur",
    "787": "NoDur",
    "788": "NoDur",
    "789": "NoDur",
    "790": "NoDur",
    "791": "NoDur",
    "792": "NoDur",
    "793": "NoDur",
    "794": "NoDur",
    "795": "NoDur",
    "796": "NoDur",
    "797": "NoDur",
    "798": "NoDur",
    "799": "NoDur",
    "800": "NoDur",
    "801": "NoDur",
    "802": "NoDur",
    "803": "NoDur",
    "804": "NoDur",
    "805": "NoDur",
    "806": "NoDur",
    "807": "NoDur",
    "808": "NoDur",
    "809": "NoDur",
    "810": "NoDur",
    "811": "NoDur",
    "812": "NoDur",
    "813": "NoDur",
    "814": "NoDur",
    "815": "NoDur",
    "816": "NoDur",
    "817": "NoDur",
    "818": "NoDur",
    "819": "NoDur",
    "820": "NoDur",
    "821": "NoDur",
    "822": "NoDur",
    "823": "NoDur",
    "824": "NoDur",
    "825": "NoDur",
    "826": "NoDur",
    "827": "NoDur",
    "828": "NoDur",
    "829": "NoDur",
    "830": "NoDur",
    "831": "NoDur",
    "832": "NoDur",
    "833": "NoDur",
    "834": "NoDur",
    "835": "NoDur",
    "836": "NoDur",
    "837": "NoDur",
    "838": "NoDur",
    "839": "NoDur",
    "840": "NoDur",
    "841": "NoDur",
    "842": "NoDur",
    "843": "NoDur",
    "844": "NoDur",
    "845": "NoDur",
    "846": "NoDur",
    "847": "NoDur",
    "848": "NoDur",
    "849": "NoDur",
    "850": "NoDur",
    "851": "NoDur",
    "852": "NoDur",
    "853": "NoDur",
    "854": "NoDur",
    "855": "NoDur",
    "856": "NoDur",
    "857": "NoDur",
    "858": "NoDur",
    "859": "NoDur",
    "860": "NoDur",
    "861": "NoDur",
    "862": "NoDur",
    "863": "NoDur",
    "864": "NoDur",
    "865": "NoDur",
    "866": "NoDur",
    "867": "NoDur",
    "868": "NoDur",
    "869": "NoDur",
    "870": "NoDur",
    "871": "NoDur",
    "872": "NoDur",
    "873": "NoDur",
    "874": "NoDur",
    "875": "NoDur",
    "876": "NoDur",
    "877": "NoDur",
    "878": "NoDur",
    "879": "NoDur",
    "880": "NoDur",
    "881": "NoDur",
    "882": "NoDur",
    "883": "NoDur",
    "884": "NoDur",
    "885": "NoDur",
    "886": "NoDur",
    "887": "NoDur",
    "888": "NoDur",
    "889": "NoDur",
    "890": "NoDur",
    "891": "NoDur",
    "892": "NoDur",
    "893": "NoDur",
    "894": "NoDur",
    "895": "NoDur",
    "896": "NoDur",
    "897": "NoDur",
    "898": "NoDur",
    "899": "NoDur",
    "900": "NoDur",
    "901": "NoDur",
    "902": "NoDur",
    "903": "NoDur",
    "904": "NoDur",
    "905": "NoDur",
    "906": "NoDur",
    "907": "NoDur",
    "908": "NoDur",
    "909": "NoDur",
    "910": "NoDur",
    "911": "NoDur",
    "912": "NoDur",
    "913": "NoDur",
    "914": "NoDur",
    "915": "NoDur",
    "916": "NoDur",
    "917": "NoDur",
    "918": "NoDur",
    "919": "NoDur",
    "920": "NoDur",
    "921": "NoDur",
    "922": "NoDur",
    "923": "NoDur",
    "924": "NoDur",
    "925": "NoDur",
    "926": "NoDur",
    "927": "NoDur",
    "928": "NoDur",
    "929": "NoDur",
    "930": "NoDur",
    "931": "NoDur",
    "932": "NoDur",
    "933": "NoDur",
    "934": "NoDur",
    "935": "NoDur",
    "936": "NoDur",
    "937": "NoDur",
    "938": "NoDur",
    "939": "NoDur",
    "940": "NoDur",
    "941": "NoDur",
    "942": "NoDur",
    "943": "NoDur",
    "944": "NoDur",
    "945": "NoDur",
    "946": "NoDur",
    "947": "NoDur",
    "948": "NoDur",
    "949": "NoDur",
    "950": "NoDur",
    "951": "NoDur",
    "952": "NoDur",
    "953": "NoDur",
    "954": "NoDur",
    "955": "NoDur",
    "956": "NoDur",
    "957": "NoDur",
    "958": "NoDur",
    "959": "NoDur",
    "960": "NoDur",
    "961": "NoDur",
    "962": "NoDur",
    "963": "NoDur",
    "964": "NoDur",
    "965": "NoDur",
    "966": "NoDur",
    "967": "NoDur",
    "968": "NoDur",
    "969": "NoDur",
    "970": "NoDur",
    "971": "NoDur",
    "972": "NoDur",
    "973": "NoDur",
    "974": "NoDur",
    "975": "NoDur",
    "976": "NoDur",
    "977": "NoDur",
    "978": "NoDur",
    "979": "NoDur",
    "980": "NoDur",
    "981": "NoDur",
    "982": "NoDur",
    "983": "NoDur",
    "984": "NoDur",
    "985": "NoDur",
    "986": "NoDur",
    "987": "NoDur",
    "988": "NoDur",
    "989": "NoDur",
    "990": "NoDur",
    "991": "NoDur",
    "992": "NoDur",
    "993": "NoDur",
    "994": "NoDur",
    "995": "NoDur",
    "996": "NoDur",
    "997": "NoDur",
    "998": "NoDur",
    "999": "NoDur",
    "2000": "NoDur",
    "2001": "NoDur",
    "2002": "NoDur",
    "2003": "NoDur",
    "2004": "NoDur",
    "2005": "NoDur",
    "2006": "NoDur",
    "2007": "NoDur",
    "2008": "NoDur",
    "2009": "NoDur",
    "2010": "NoDur",
    "2011": "NoDur",
    "2012": "NoDur",
    "2013": "NoDur",
    "2014": "NoDur",
    "2015": "NoDur",
    "2016": "NoDur",
    "2017": "NoDur",
    "2018": "NoDur",
    "2019": "NoDur",
    "2020": "NoDur",
    "2021": "NoDur",
    "2022": "NoDur",
    "2023": "NoDur",
    "2024": "NoDur",
    "2025": "NoDur",
    "2026": "NoDur",
    "2027": "NoDur",
    "2028": "NoDur",
    "2029": "NoDur",
    "2030": "NoDur",
    "2031": "NoDur",
    "2032": "NoDur",
    "2033": "NoDur",
    "2034": "NoDur",
    "2035": "NoDur",
    "2036": "NoDur",
    "2037": "NoDur",
    "2038": "NoDur",
    "2039": "NoDur",
    "2040": "NoDur",
    "2041": "NoDur",
    "2042": "NoDur",
    "2043": "NoDur",
    "2044": "NoDur",
    "2045": "NoDur",
    "2046": "NoDur",
    "2047": "NoDur",
    "2048": "NoDur",
    "2049": "NoDur",
    "2050": "NoDur",
    "2051": "NoDur",
    "2052": "NoDur",
    "2053": "NoDur",
    "2054": "NoDur",
    "2055": "NoDur",
    "2056": "NoDur",
    "2057": "NoDur",
    "2058": "NoDur",
    "2059": "NoDur",
    "2060": "NoDur",
    "2061": "NoDur",
    "2062": "NoDur",
    "2063": "NoDur",
    "2064": "NoDur",
    "2065": "NoDur",
    "2066": "NoDur",
    "2067": "NoDur",
    "2068": "NoDur",
    "2069": "NoDur",
    "2070": "NoDur",
    "2071": "NoDur",
    "2072": "NoDur",
    "2073": "NoDur",
    "2074": "NoDur",
    "2075": "NoDur",
    "2076": "NoDur",
    "2077": "NoDur",
    "2078": "NoDur",
    "2079": "NoDur",
    "2080": "NoDur",
    "2081": "NoDur",
    "2082": "NoDur",
    "2083": "NoDur",
    "2084": "NoDur",
    "2085": "NoDur",
    "2086": "NoDur",
    "2087": "NoDur",
    "2088": "NoDur",
    "2089": "NoDur",
    "2090": "NoDur",
    "2091": "NoDur",
    "2092": "NoDur",
    "2093": "NoDur",
    "2094": "NoDur",
    "2095": "NoDur",
    "2096": "NoDur",
    "2097": "NoDur",
    "2098": "NoDur",
    "2099": "NoDur",
    "2100": "NoDur",
    "2101": "NoDur",
    "2102": "NoDur",
    "2103": "NoDur",
    "2104": "NoDur",
    "2105": "NoDur",
    "2106": "NoDur",
    "2107": "NoDur",
    "2108": "NoDur",
    "2109": "NoDur",
    "2110": "NoDur",
    "2111": "NoDur",
    "2112": "NoDur",
    "2113": "NoDur",
    "2114": "NoDur",
    "2115": "NoDur",
    "2116": "NoDur",
    "2117": "NoDur",
    "2118": "NoDur",
    "2119": "NoDur",
    "2120": "NoDur",
    "2121": "NoDur",
    "2122": "NoDur",
    "2123": "NoDur",
    "2124": "NoDur",
    "2125": "NoDur",
    "2126": "NoDur",
    "2127": "NoDur",
    "2128": "NoDur",
    "2129": "NoDur",
    "2130": "NoDur",
    "2131": "NoDur",
    "2132": "NoDur",
    "2133": "NoDur",
    "2134": "NoDur",
    "2135": "NoDur",
    "2136": "NoDur",
    "2137": "NoDur",
    "2138": "NoDur",
    "2139": "NoDur",
    "2140": "NoDur",
    "2141": "NoDur",
    "2142": "NoDur",
    "2143": "NoDur",
    "2144": "NoDur",
    "2145": "NoDur",
    "2146": "NoDur",
    "2147": "NoDur",
    "2148": "NoDur",
    "2149": "NoDur",
    "2150": "NoDur",
    "2151": "NoDur",
    "2152": "NoDur",
    "2153": "NoDur",
    "2154": "NoDur",
    "2155": "NoDur",
    "2156": "NoDur",
    "2157": "NoDur",
    "2158": "NoDur",
    "2159": "NoDur",
    "2160": "NoDur",
    "2161": "NoDur",
    "2162": "NoDur",
    "2163": "NoDur",
    "2164": "NoDur",
    "2165": "NoDur",
    "2166": "NoDur",
    "2167": "NoDur",
    "2168": "NoDur",
    "2169": "NoDur",
    "2170": "NoDur",
    "2171": "NoDur",
    "2172": "NoDur",
    "2173": "NoDur",
    "2174": "NoDur",
    "2175": "NoDur",
    "2176": "NoDur",
    "2177": "NoDur",
    "2178": "NoDur",
    "2179": "NoDur",
    "2180": "NoDur",
    "2181": "NoDur",
    "2182": "NoDur",
    "2183": "NoDur",
    "2184": "NoDur",
    "2185": "NoDur",
    "2186": "NoDur",
    "2187": "NoDur",
    "2188": "NoDur",
    "2189": "NoDur",
    "2190": "NoDur",
    "2191": "NoDur",
    "2192": "NoDur",
    "2193": "NoDur",
    "2194": "NoDur",
    "2195": "NoDur",
    "2196": "NoDur",
    "2197": "NoDur",
    "2198": "NoDur",
    "2199": "NoDur",
    "2200": "NoDur",
    "2201": "NoDur",
    "2202": "NoDur",
    "2203": "NoDur",
    "2204": "NoDur",
    "2205": "NoDur",
    "2206": "NoDur",
    "2207": "NoDur",
    "2208": "NoDur",
    "2209": "NoDur",
    "2210": "NoDur",
    "2211": "NoDur",
    "2212": "NoDur",
    "2213": "NoDur",
    "2214": "NoDur",
    "2215": "NoDur",
    "2216": "NoDur",
    "2217": "NoDur",
    "2218": "NoDur",
    "2219": "NoDur",
    "2220": "NoDur",
    "2221": "NoDur",
    "2222": "NoDur",
    "2223": "NoDur",
    "2224": "NoDur",
    "2225": "NoDur",
    "2226": "NoDur",
    "2227": "NoDur",
    "2228": "NoDur",
    "2229": "NoDur",
    "2230": "NoDur",
    "2231": "NoDur",
    "2232": "NoDur",
    "2233": "NoDur",
    "2234": "NoDur",
    "2235": "NoDur",
    "2236": "NoDur",
    "2237": "NoDur",
    "2238": "NoDur",
    "2239": "NoDur",
    "2240": "NoDur",
    "2241": "NoDur",
    "2242": "NoDur",
    "2243": "NoDur",
    "2244": "NoDur",
    "2245": "NoDur",
    "2246": "NoDur",
    "2247": "NoDur",
    "2248": "NoDur",
    "2249": "NoDur",
    "2250": "NoDur",
    "2251": "NoDur",
    "2252": "NoDur",
    "2253": "NoDur",
    "2254": "NoDur",
    "2255": "NoDur",
    "2256": "NoDur",
    "2257": "NoDur",
    "2258": "NoDur",
    "2259": "NoDur",
    "2260": "NoDur",
    "2261": "NoDur",
    "2262": "NoDur",
    "2263": "NoDur",
    "2264": "NoDur",
    "2265": "NoDur",
    "2266": "NoDur",
    "2267": "NoDur",
    "2268": "NoDur",
    "2269": "NoDur",
    "2270": "NoDur",
    "2271": "NoDur",
    "2272": "NoDur",
    "2273": "NoDur",
    "2274": "NoDur",
    "2275": "NoDur",
    "2276": "NoDur",
    "2277": "NoDur",
    "2278": "NoDur",
    "2279": "NoDur",
    "2280": "NoDur",
    "2281": "NoDur",
    "2282": "NoDur",
    "2283": "NoDur",
    "2284": "NoDur",
    "2285": "NoDur",
    "2286": "NoDur",
    "2287": "NoDur",
    "2288": "NoDur",
    "2289": "NoDur",
    "2290": "NoDur",
    "2291": "NoDur",
    "2292": "NoDur",
    "2293": "NoDur",
    "2294": "NoDur",
    "2295": "NoDur",
    "2296": "NoDur",
    "2297": "NoDur",
    "2298": "NoDur",
    "2299": "NoDur",
    "2300": "NoDur",
    "2301": "NoDur",
    "2302": "NoDur",
    "2303": "NoDur",
    "2304": "NoDur",
    "2305": "NoDur",
    "2306": "NoDur",
    "2307": "NoDur",
    "2308": "NoDur",
    "2309": "NoDur",
    "2310": "NoDur",
    "2311": "NoDur",
    "2312": "NoDur",
    "2313": "NoDur",
    "2314": "NoDur",
    "2315": "NoDur",
    "2316": "NoDur",
    "2317": "NoDur",
    "2318": "NoDur",
    "2319": "NoDur",
    "2320": "NoDur",
    "2321": "NoDur",
    "2322": "NoDur",
    "2323": "NoDur",
    "2324": "NoDur",
    "2325": "NoDur",
    "2326": "NoDur",
    "2327": "NoDur",
    "2328": "NoDur",
    "2329": "NoDur",
    "2330": "NoDur",
    "2331": "NoDur",
    "2332": "NoDur",
    "2333": "NoDur",
    "2334": "NoDur",
    "2335": "NoDur",
    "2336": "NoDur",
    "2337": "NoDur",
    "2338": "NoDur",
    "2339": "NoDur",
    "2340": "NoDur",
    "2341": "NoDur",
    "2342": "NoDur",
    "2343": "NoDur",
    "2344": "NoDur",
    "2345": "NoDur",
    "2346": "NoDur",
    "2347": "NoDur",
    "2348": "NoDur",
    "2349": "NoDur",
    "2350": "NoDur",
    "2351": "NoDur",
    "2352": "NoDur",
    "2353": "NoDur",
    "2354": "NoDur",
    "2355": "NoDur",
    "2356": "NoDur",
    "2357": "NoDur",
    "2358": "NoDur",
    "2359": "NoDur",
    "2360": "NoDur",
    "2361": "NoDur",
    "2362": "NoDur",
    "2363": "NoDur",
    "2364": "NoDur",
    "2365": "NoDur",
    "2366": "NoDur",
    "2367": "NoDur",
    "2368": "NoDur",
    "2369": "NoDur",
    "2370": "NoDur",
    "2371": "NoDur",
    "2372": "NoDur",
    "2373": "NoDur",
    "2374": "NoDur",
    "2375": "NoDur",
    "2376": "NoDur",
    "2377": "NoDur",
    "2378": "NoDur",
    "2379": "NoDur",
    "2380": "NoDur",
    "2381": "NoDur",
    "2382": "NoDur",
    "2383": "NoDur",
    "2384": "NoDur",
    "2385": "NoDur",
    "2386": "NoDur",
    "2387": "NoDur",
    "2388": "NoDur",
    "2389": "NoDur",
    "2390": "NoDur",
    "2391": "NoDur",
    "2392": "NoDur",
    "2393": "NoDur",
    "2394": "NoDur",
    "2395": "NoDur",
    "2396": "NoDur",
    "2397": "NoDur",
    "2398": "NoDur",
    "2399": "NoDur",
    "2700": "NoDur",
    "2701": "NoDur",
    "2702": "NoDur",
    "2703": "NoDur",
    "2704": "NoDur",
    "2705": "NoDur",
    "2706": "NoDur",
    "2707": "NoDur",
    "2708": "NoDur",
    "2709": "NoDur",
    "2710": "NoDur",
    "2711": "NoDur",
    "2712": "NoDur",
    "2713": "NoDur",
    "2714": "NoDur",
    "2715": "NoDur",
    "2716": "NoDur",
    "2717": "NoDur",
    "2718": "NoDur",
    "2719": "NoDur",
    "2720": "NoDur",
    "2721": "NoDur",
    "2722": "NoDur",
    "2723": "NoDur",
    "2724": "NoDur",
    "2725": "NoDur",
    "2726": "NoDur",
    "2727": "NoDur",
    "2728": "NoDur",
    "2729": "NoDur",
    "2730": "NoDur",
    "2731": "NoDur",
    "2732": "NoDur",
    "2733": "NoDur",
    "2734": "NoDur",
    "2735": "NoDur",
    "2736": "NoDur",
    "2737": "NoDur",
    "2738": "NoDur",
    "2739": "NoDur",
    "2740": "NoDur",
    "2741": "NoDur",
    "2742": "NoDur",
    "2743": "NoDur",
    "2744": "NoDur",
    "2745": "NoDur",
    "2746": "NoDur",
    "2747": "NoDur",
    "2748": "NoDur",
    "2749": "NoDur",
    "2770": "NoDur",
    "2771": "NoDur",
    "2772": "NoDur",
    "2773": "NoDur",
    "2774": "NoDur",
    "2775": "NoDur",
    "2776": "NoDur",
    "2777": "NoDur",
    "2778": "NoDur",
    "2779": "NoDur",
    "2780": "NoDur",
    "2781": "NoDur",
    "2782": "NoDur",
    "2783": "NoDur",
    "2784": "NoDur",
    "2785": "NoDur",
    "2786": "NoDur",
    "2787": "NoDur",
    "2788": "NoDur",
    "2789": "NoDur",
    "2790": "NoDur",
    "2791": "NoDur",
    "2792": "NoDur",
    "2793": "NoDur",
    "2794": "NoDur",
    "2795": "NoDur",
    "2796": "NoDur",
    "2797": "NoDur",
    "2798": "NoDur",
    "2799": "NoDur",
    "3100": "NoDur",
    "3101": "NoDur",
    "3102": "NoDur",
    "3103": "NoDur",
    "3104": "NoDur",
    "3105": "NoDur",
    "3106": "NoDur",
    "3107": "NoDur",
    "3108": "NoDur",
    "3109": "NoDur",
    "3110": "NoDur",
    "3111": "NoDur",
    "3112": "NoDur",
    "3113": "NoDur",
    "3114": "NoDur",
    "3115": "NoDur",
    "3116": "NoDur",
    "3117": "NoDur",
    "3118": "NoDur",
    "3119": "NoDur",
    "3120": "NoDur",
    "3121": "NoDur",
    "3122": "NoDur",
    "3123": "NoDur",
    "3124": "NoDur",
    "3125": "NoDur",
    "3126": "NoDur",
    "3127": "NoDur",
    "3128": "NoDur",
    "3129": "NoDur",
    "3130": "NoDur",
    "3131": "NoDur",
    "3132": "NoDur",
    "3133": "NoDur",
    "3134": "NoDur",
    "3135": "NoDur",
    "3136": "NoDur",
    "3137": "NoDur",
    "3138": "NoDur",
    "3139": "NoDur",
    "3140": "NoDur",
    "3141": "NoDur",
    "3142": "NoDur",
    "3143": "NoDur",
    "3144": "NoDur",
    "3145": "NoDur",
    "3146": "NoDur",
    "3147": "NoDur",
    "3148": "NoDur",
    "3149": "NoDur",
    "3150": "NoDur",
    "3151": "NoDur",
    "3152": "NoDur",
    "3153": "NoDur",
    "3154": "NoDur",
    "3155": "NoDur",
    "3156": "NoDur",
    "3157": "NoDur",
    "3158": "NoDur",
    "3159": "NoDur",
    "3160": "NoDur",
    "3161": "NoDur",
    "3162": "NoDur",
    "3163": "NoDur",
    "3164": "NoDur",
    "3165": "NoDur",
    "3166": "NoDur",
    "3167": "NoDur",
    "3168": "NoDur",
    "3169": "NoDur",
    "3170": "NoDur",
    "3171": "NoDur",
    "3172": "NoDur",
    "3173": "NoDur",
    "3174": "NoDur",
    "3175": "NoDur",
    "3176": "NoDur",
    "3177": "NoDur",
    "3178": "NoDur",
    "3179": "NoDur",
    "3180": "NoDur",
    "3181": "NoDur",
    "3182": "NoDur",
    "3183": "NoDur",
    "3184": "NoDur",
    "3185": "NoDur",
    "3186": "NoDur",
    "3187": "NoDur",
    "3188": "NoDur",
    "3189": "NoDur",
    "3190": "NoDur",
    "3191": "NoDur",
    "3192": "NoDur",
    "3193": "NoDur",
    "3194": "NoDur",
    "3195": "NoDur",
    "3196": "NoDur",
    "3197": "NoDur",
    "3198": "NoDur",
    "3199": "NoDur",
    "3940": "NoDur",
    "3941": "NoDur",
    "3942": "NoDur",
    "3943": "NoDur",
    "3944": "NoDur",
    "3945": "NoDur",
    "3946": "NoDur",
    "3947": "NoDur",
    "3948": "NoDur",
    "3949": "NoDur",
    "3950": "NoDur",
    "3951": "NoDur",
    "3952": "NoDur",
    "3953": "NoDur",
    "3954": "NoDur",
    "3955": "NoDur",
    "3956": "NoDur",
    "3957": "NoDur",
    "3958": "NoDur",
    "3959": "NoDur",
    "3960": "NoDur",
    "3961": "NoDur",
    "3962": "NoDur",
    "3963": "NoDur",
    "3964": "NoDur",
    "3965": "NoDur",
    "3966": "NoDur",
    "3967": "NoDur",
    "3968": "NoDur",
    "3969": "NoDur",
    "3970": "NoDur",
    "3971": "NoDur",
    "3972": "NoDur",
    "3973": "NoDur",
    "3974": "NoDur",
    "3975": "NoDur",
    "3976": "NoDur",
    "3977": "NoDur",
    "3978": "NoDur",
    "3979": "NoDur",
    "3980": "NoDur",
    "3981": "NoDur",
    "3982": "NoDur",
    "3983": "NoDur",
    "3984": "NoDur",
    "3985": "NoDur",
    "3986": "NoDur",
    "3987": "NoDur",
    "3988": "NoDur",
    "3989": "NoDur",
    "2500": "Durbl",
    "2501": "Durbl",
    "2502": "Durbl",
    "2503": "Durbl",
    "2504": "Durbl",
    "2505": "Durbl",
    "2506": "Durbl",
    "2507": "Durbl",
    "2508": "Durbl",
    "2509": "Durbl",
    "2510": "Durbl",
    "2511": "Durbl",
    "2512": "Durbl",
    "2513": "Durbl",
    "2514": "Durbl",
    "2515": "Durbl",
    "2516": "Durbl",
    "2517": "Durbl",
    "2518": "Durbl",
    "2519": "Durbl",
    "2590": "Durbl",
    "2591": "Durbl",
    "2592": "Durbl",
    "2593": "Durbl",
    "2594": "Durbl",
    "2595": "Durbl",
    "2596": "Durbl",
    "2597": "Durbl",
    "2598": "Durbl",
    "2599": "Durbl",
    "3630": "Durbl",
    "3631": "Durbl",
    "3632": "Durbl",
    "3633": "Durbl",
    "3634": "Durbl",
    "3635": "Durbl",
    "3636": "Durbl",
    "3637": "Durbl",
    "3638": "Durbl",
    "3639": "Durbl",
    "3640": "Durbl",
    "3641": "Durbl",
    "3642": "Durbl",
    "3643": "Durbl",
    "3644": "Durbl",
    "3645": "Durbl",
    "3646": "Durbl",
    "3647": "Durbl",
    "3648": "Durbl",
    "3649": "Durbl",
    "3650": "Durbl",
    "3651": "Durbl",
    "3652": "Durbl",
    "3653": "Durbl",
    "3654": "Durbl",
    "3655": "Durbl",
    "3656": "Durbl",
    "3657": "Durbl",
    "3658": "Durbl",
    "3659": "Durbl",
    "3710": "Durbl",
    "3711": "Durbl",
    "3714": "Durbl",
    "3716": "Durbl",
    "3750": "Durbl",
    "3751": "Durbl",
    "3792": "Durbl",
    "3900": "Durbl",
    "3901": "Durbl",
    "3902": "Durbl",
    "3903": "Durbl",
    "3904": "Durbl",
    "3905": "Durbl",
    "3906": "Durbl",
    "3907": "Durbl",
    "3908": "Durbl",
    "3909": "Durbl",
    "3910": "Durbl",
    "3911": "Durbl",
    "3912": "Durbl",
    "3913": "Durbl",
    "3914": "Durbl",
    "3915": "Durbl",
    "3916": "Durbl",
    "3917": "Durbl",
    "3918": "Durbl",
    "3919": "Durbl",
    "3920": "Durbl",
    "3921": "Durbl",
    "3922": "Durbl",
    "3923": "Durbl",
    "3924": "Durbl",
    "3925": "Durbl",
    "3926": "Durbl",
    "3927": "Durbl",
    "3928": "Durbl",
    "3929": "Durbl",
    "3930": "Durbl",
    "3931": "Durbl",
    "3932": "Durbl",
    "3933": "Durbl",
    "3934": "Durbl",
    "3935": "Durbl",
    "3936": "Durbl",
    "3937": "Durbl",
    "3938": "Durbl",
    "3939": "Durbl",
    "3990": "Durbl",
    "3991": "Durbl",
    "3992": "Durbl",
    "3993": "Durbl",
    "3994": "Durbl",
    "3995": "Durbl",
    "3996": "Durbl",
    "3997": "Durbl",
    "3998": "Durbl",
    "3999": "Durbl",
    "2520": "Manuf",
    "2521": "Manuf",
    "2522": "Manuf",
    "2523": "Manuf",
    "2524": "Manuf",
    "2525": "Manuf",
    "2526": "Manuf",
    "2527": "Manuf",
    "2528": "Manuf",
    "2529": "Manuf",
    "2530": "Manuf",
    "2531": "Manuf",
    "2532": "Manuf",
    "2533": "Manuf",
    "2534": "Manuf",
    "2535": "Manuf",
    "2536": "Manuf",
    "2537": "Manuf",
    "2538": "Manuf",
    "2539": "Manuf",
    "2540": "Manuf",
    "2541": "Manuf",
    "2542": "Manuf",
    "2543": "Manuf",
    "2544": "Manuf",
    "2545": "Manuf",
    "2546": "Manuf",
    "2547": "Manuf",
    "2548": "Manuf",
    "2549": "Manuf",
    "2550": "Manuf",
    "2551": "Manuf",
    "2552": "Manuf",
    "2553": "Manuf",
    "2554": "Manuf",
    "2555": "Manuf",
    "2556": "Manuf",
    "2557": "Manuf",
    "2558": "Manuf",
    "2559": "Manuf",
    "2560": "Manuf",
    "2561": "Manuf",
    "2562": "Manuf",
    "2563": "Manuf",
    "2564": "Manuf",
    "2565": "Manuf",
    "2566": "Manuf",
    "2567": "Manuf",
    "2568": "Manuf",
    "2569": "Manuf",
    "2570": "Manuf",
    "2571": "Manuf",
    "2572": "Manuf",
    "2573": "Manuf",
    "2574": "Manuf",
    "2575": "Manuf",
    "2576": "Manuf",
    "2577": "Manuf",
    "2578": "Manuf",
    "2579": "Manuf",
    "2580": "Manuf",
    "2581": "Manuf",
    "2582": "Manuf",
    "2583": "Manuf",
    "2584": "Manuf",
    "2585": "Manuf",
    "2586": "Manuf",
    "2587": "Manuf",
    "2588": "Manuf",
    "2589": "Manuf",
    "2600": "Manuf",
    "2601": "Manuf",
    "2602": "Manuf",
    "2603": "Manuf",
    "2604": "Manuf",
    "2605": "Manuf",
    "2606": "Manuf",
    "2607": "Manuf",
    "2608": "Manuf",
    "2609": "Manuf",
    "2610": "Manuf",
    "2611": "Manuf",
    "2612": "Manuf",
    "2613": "Manuf",
    "2614": "Manuf",
    "2615": "Manuf",
    "2616": "Manuf",
    "2617": "Manuf",
    "2618": "Manuf",
    "2619": "Manuf",
    "2620": "Manuf",
    "2621": "Manuf",
    "2622": "Manuf",
    "2623": "Manuf",
    "2624": "Manuf",
    "2625": "Manuf",
    "2626": "Manuf",
    "2627": "Manuf",
    "2628": "Manuf",
    "2629": "Manuf",
    "2630": "Manuf",
    "2631": "Manuf",
    "2632": "Manuf",
    "2633": "Manuf",
    "2634": "Manuf",
    "2635": "Manuf",
    "2636": "Manuf",
    "2637": "Manuf",
    "2638": "Manuf",
    "2639": "Manuf",
    "2640": "Manuf",
    "2641": "Manuf",
    "2642": "Manuf",
    "2643": "Manuf",
    "2644": "Manuf",
    "2645": "Manuf",
    "2646": "Manuf",
    "2647": "Manuf",
    "2648": "Manuf",
    "2649": "Manuf",
    "2650": "Manuf",
    "2651": "Manuf",
    "2652": "Manuf",
    "2653": "Manuf",
    "2654": "Manuf",
    "2655": "Manuf",
    "2656": "Manuf",
    "2657": "Manuf",
    "2658": "Manuf",
    "2659": "Manuf",
    "2660": "Manuf",
    "2661": "Manuf",
    "2662": "Manuf",
    "2663": "Manuf",
    "2664": "Manuf",
    "2665": "Manuf",
    "2666": "Manuf",
    "2667": "Manuf",
    "2668": "Manuf",
    "2669": "Manuf",
    "2670": "Manuf",
    "2671": "Manuf",
    "2672": "Manuf",
    "2673": "Manuf",
    "2674": "Manuf",
    "2675": "Manuf",
    "2676": "Manuf",
    "2677": "Manuf",
    "2678": "Manuf",
    "2679": "Manuf",
    "2680": "Manuf",
    "2681": "Manuf",
    "2682": "Manuf",
    "2683": "Manuf",
    "2684": "Manuf",
    "2685": "Manuf",
    "2686": "Manuf",
    "2687": "Manuf",
    "2688": "Manuf",
    "2689": "Manuf",
    "2690": "Manuf",
    "2691": "Manuf",
    "2692": "Manuf",
    "2693": "Manuf",
    "2694": "Manuf",
    "2695": "Manuf",
    "2696": "Manuf",
    "2697": "Manuf",
    "2698": "Manuf",
    "2699": "Manuf",
    "2750": "Manuf",
    "2751": "Manuf",
    "2752": "Manuf",
    "2753": "Manuf",
    "2754": "Manuf",
    "2755": "Manuf",
    "2756": "Manuf",
    "2757": "Manuf",
    "2758": "Manuf",
    "2759": "Manuf",
    "2760": "Manuf",
    "2761": "Manuf",
    "2762": "Manuf",
    "2763": "Manuf",
    "2764": "Manuf",
    "2765": "Manuf",
    "2766": "Manuf",
    "2767": "Manuf",
    "2768": "Manuf",
    "2769": "Manuf",
    "2800": "Manuf",
    "2801": "Manuf",
    "2802": "Manuf",
    "2803": "Manuf",
    "2804": "Manuf",
    "2805": "Manuf",
    "2806": "Manuf",
    "2807": "Manuf",
    "2808": "Manuf",
    "2809": "Manuf",
    "2810": "Manuf",
    "2811": "Manuf",
    "2812": "Manuf",
    "2813": "Manuf",
    "2814": "Manuf",
    "2815": "Manuf",
    "2816": "Manuf",
    "2817": "Manuf",
    "2818": "Manuf",
    "2819": "Manuf",
    "2820": "Manuf",
    "2821": "Manuf",
    "2822": "Manuf",
    "2823": "Manuf",
    "2824": "Manuf",
    "2825": "Manuf",
    "2826": "Manuf",
    "2827": "Manuf",
    "2828": "Manuf",
    "2829": "Manuf",
    "2840": "Manuf",
    "2841": "Manuf",
    "2842": "Manuf",
    "2843": "Manuf",
    "2844": "Manuf",
    "2845": "Manuf",
    "2846": "Manuf",
    "2847": "Manuf",
    "2848": "Manuf",
    "2849": "Manuf",
    "2850": "Manuf",
    "2851": "Manuf",
    "2852": "Manuf",
    "2853": "Manuf",
    "2854": "Manuf",
    "2855": "Manuf",
    "2856": "Manuf",
    "2857": "Manuf",
    "2858": "Manuf",
    "2859": "Manuf",
    "2860": "Manuf",
    "2861": "Manuf",
    "2862": "Manuf",
    "2863": "Manuf",
    "2864": "Manuf",
    "2865": "Manuf",
    "2866": "Manuf",
    "2867": "Manuf",
    "2868": "Manuf",
    "2869": "Manuf",
    "2870": "Manuf",
    "2871": "Manuf",
    "2872": "Manuf",
    "2873": "Manuf",
    "2874": "Manuf",
    "2875": "Manuf",
    "2876": "Manuf",
    "2877": "Manuf",
    "2878": "Manuf",
    "2879": "Manuf",
    "2880": "Manuf",
    "2881": "Manuf",
    "2882": "Manuf",
    "2883": "Manuf",
    "2884": "Manuf",
    "2885": "Manuf",
    "2886": "Manuf",
    "2887": "Manuf",
    "2888": "Manuf",
    "2889": "Manuf",
    "2890": "Manuf",
    "2891": "Manuf",
    "2892": "Manuf",
    "2893": "Manuf",
    "2894": "Manuf",
    "2895": "Manuf",
    "2896": "Manuf",
    "2897": "Manuf",
    "2898": "Manuf",
    "2899": "Manuf",
    "3000": "Manuf",
    "3001": "Manuf",
    "3002": "Manuf",
    "3003": "Manuf",
    "3004": "Manuf",
    "3005": "Manuf",
    "3006": "Manuf",
    "3007": "Manuf",
    "3008": "Manuf",
    "3009": "Manuf",
    "3010": "Manuf",
    "3011": "Manuf",
    "3012": "Manuf",
    "3013": "Manuf",
    "3014": "Manuf",
    "3015": "Manuf",
    "3016": "Manuf",
    "3017": "Manuf",
    "3018": "Manuf",
    "3019": "Manuf",
    "3020": "Manuf",
    "3021": "Manuf",
    "3022": "Manuf",
    "3023": "Manuf",
    "3024": "Manuf",
    "3025": "Manuf",
    "3026": "Manuf",
    "3027": "Manuf",
    "3028": "Manuf",
    "3029": "Manuf",
    "3030": "Manuf",
    "3031": "Manuf",
    "3032": "Manuf",
    "3033": "Manuf",
    "3034": "Manuf",
    "3035": "Manuf",
    "3036": "Manuf",
    "3037": "Manuf",
    "3038": "Manuf",
    "3039": "Manuf",
    "3040": "Manuf",
    "3041": "Manuf",
    "3042": "Manuf",
    "3043": "Manuf",
    "3044": "Manuf",
    "3045": "Manuf",
    "3046": "Manuf",
    "3047": "Manuf",
    "3048": "Manuf",
    "3049": "Manuf",
    "3050": "Manuf",
    "3051": "Manuf",
    "3052": "Manuf",
    "3053": "Manuf",
    "3054": "Manuf",
    "3055": "Manuf",
    "3056": "Manuf",
    "3057": "Manuf",
    "3058": "Manuf",
    "3059": "Manuf",
    "3060": "Manuf",
    "3061": "Manuf",
    "3062": "Manuf",
    "3063": "Manuf",
    "3064": "Manuf",
    "3065": "Manuf",
    "3066": "Manuf",
    "3067": "Manuf",
    "3068": "Manuf",
    "3069": "Manuf",
    "3070": "Manuf",
    "3071": "Manuf",
    "3072": "Manuf",
    "3073": "Manuf",
    "3074": "Manuf",
    "3075": "Manuf",
    "3076": "Manuf",
    "3077": "Manuf",
    "3078": "Manuf",
    "3079": "Manuf",
    "3080": "Manuf",
    "3081": "Manuf",
    "3082": "Manuf",
    "3083": "Manuf",
    "3084": "Manuf",
    "3085": "Manuf",
    "3086": "Manuf",
    "3087": "Manuf",
    "3088": "Manuf",
    "3089": "Manuf",
    "3090": "Manuf",
    "3091": "Manuf",
    "3092": "Manuf",
    "3093": "Manuf",
    "3094": "Manuf",
    "3095": "Manuf",
    "3096": "Manuf",
    "3097": "Manuf",
    "3098": "Manuf",
    "3099": "Manuf",
    "3200": "Manuf",
    "3201": "Manuf",
    "3202": "Manuf",
    "3203": "Manuf",
    "3204": "Manuf",
    "3205": "Manuf",
    "3206": "Manuf",
    "3207": "Manuf",
    "3208": "Manuf",
    "3209": "Manuf",
    "3210": "Manuf",
    "3211": "Manuf",
    "3212": "Manuf",
    "3213": "Manuf",
    "3214": "Manuf",
    "3215": "Manuf",
    "3216": "Manuf",
    "3217": "Manuf",
    "3218": "Manuf",
    "3219": "Manuf",
    "3220": "Manuf",
    "3221": "Manuf",
    "3222": "Manuf",
    "3223": "Manuf",
    "3224": "Manuf",
    "3225": "Manuf",
    "3226": "Manuf",
    "3227": "Manuf",
    "3228": "Manuf",
    "3229": "Manuf",
    "3230": "Manuf",
    "3231": "Manuf",
    "3232": "Manuf",
    "3233": "Manuf",
    "3234": "Manuf",
    "3235": "Manuf",
    "3236": "Manuf",
    "3237": "Manuf",
    "3238": "Manuf",
    "3239": "Manuf",
    "3240": "Manuf",
    "3241": "Manuf",
    "3242": "Manuf",
    "3243": "Manuf",
    "3244": "Manuf",
    "3245": "Manuf",
    "3246": "Manuf",
    "3247": "Manuf",
    "3248": "Manuf",
    "3249": "Manuf",
    "3250": "Manuf",
    "3251": "Manuf",
    "3252": "Manuf",
    "3253": "Manuf",
    "3254": "Manuf",
    "3255": "Manuf",
    "3256": "Manuf",
    "3257": "Manuf",
    "3258": "Manuf",
    "3259": "Manuf",
    "3260": "Manuf",
    "3261": "Manuf",
    "3262": "Manuf",
    "3263": "Manuf",
    "3264": "Manuf",
    "3265": "Manuf",
    "3266": "Manuf",
    "3267": "Manuf",
    "3268": "Manuf",
    "3269": "Manuf",
    "3270": "Manuf",
    "3271": "Manuf",
    "3272": "Manuf",
    "3273": "Manuf",
    "3274": "Manuf",
    "3275": "Manuf",
    "3276": "Manuf",
    "3277": "Manuf",
    "3278": "Manuf",
    "3279": "Manuf",
    "3280": "Manuf",
    "3281": "Manuf",
    "3282": "Manuf",
    "3283": "Manuf",
    "3284": "Manuf",
    "3285": "Manuf",
    "3286": "Manuf",
    "3287": "Manuf",
    "3288": "Manuf",
    "3289": "Manuf",
    "3290": "Manuf",
    "3291": "Manuf",
    "3292": "Manuf",
    "3293": "Manuf",
    "3294": "Manuf",
    "3295": "Manuf",
    "3296": "Manuf",
    "3297": "Manuf",
    "3298": "Manuf",
    "3299": "Manuf",
    "3300": "Manuf",
    "3301": "Manuf",
    "3302": "Manuf",
    "3303": "Manuf",
    "3304": "Manuf",
    "3305": "Manuf",
    "3306": "Manuf",
    "3307": "Manuf",
    "3308": "Manuf",
    "3309": "Manuf",
    "3310": "Manuf",
    "3311": "Manuf",
    "3312": "Manuf",
    "3313": "Manuf",
    "3314": "Manuf",
    "3315": "Manuf",
    "3316": "Manuf",
    "3317": "Manuf",
    "3318": "Manuf",
    "3319": "Manuf",
    "3320": "Manuf",
    "3321": "Manuf",
    "3322": "Manuf",
    "3323": "Manuf",
    "3324": "Manuf",
    "3325": "Manuf",
    "3326": "Manuf",
    "3327": "Manuf",
    "3328": "Manuf",
    "3329": "Manuf",
    "3330": "Manuf",
    "3331": "Manuf",
    "3332": "Manuf",
    "3333": "Manuf",
    "3334": "Manuf",
    "3335": "Manuf",
    "3336": "Manuf",
    "3337": "Manuf",
    "3338": "Manuf",
    "3339": "Manuf",
    "3340": "Manuf",
    "3341": "Manuf",
    "3342": "Manuf",
    "3343": "Manuf",
    "3344": "Manuf",
    "3345": "Manuf",
    "3346": "Manuf",
    "3347": "Manuf",
    "3348": "Manuf",
    "3349": "Manuf",
    "3350": "Manuf",
    "3351": "Manuf",
    "3352": "Manuf",
    "3353": "Manuf",
    "3354": "Manuf",
    "3355": "Manuf",
    "3356": "Manuf",
    "3357": "Manuf",
    "3358": "Manuf",
    "3359": "Manuf",
    "3360": "Manuf",
    "3361": "Manuf",
    "3362": "Manuf",
    "3363": "Manuf",
    "3364": "Manuf",
    "3365": "Manuf",
    "3366": "Manuf",
    "3367": "Manuf",
    "3368": "Manuf",
    "3369": "Manuf",
    "3370": "Manuf",
    "3371": "Manuf",
    "3372": "Manuf",
    "3373": "Manuf",
    "3374": "Manuf",
    "3375": "Manuf",
    "3376": "Manuf",
    "3377": "Manuf",
    "3378": "Manuf",
    "3379": "Manuf",
    "3380": "Manuf",
    "3381": "Manuf",
    "3382": "Manuf",
    "3383": "Manuf",
    "3384": "Manuf",
    "3385": "Manuf",
    "3386": "Manuf",
    "3387": "Manuf",
    "3388": "Manuf",
    "3389": "Manuf",
    "3390": "Manuf",
    "3391": "Manuf",
    "3392": "Manuf",
    "3393": "Manuf",
    "3394": "Manuf",
    "3395": "Manuf",
    "3396": "Manuf",
    "3397": "Manuf",
    "3398": "Manuf",
    "3399": "Manuf",
    "3400": "Manuf",
    "3401": "Manuf",
    "3402": "Manuf",
    "3403": "Manuf",
    "3404": "Manuf",
    "3405": "Manuf",
    "3406": "Manuf",
    "3407": "Manuf",
    "3408": "Manuf",
    "3409": "Manuf",
    "3410": "Manuf",
    "3411": "Manuf",
    "3412": "Manuf",
    "3413": "Manuf",
    "3414": "Manuf",
    "3415": "Manuf",
    "3416": "Manuf",
    "3417": "Manuf",
    "3418": "Manuf",
    "3419": "Manuf",
    "3420": "Manuf",
    "3421": "Manuf",
    "3422": "Manuf",
    "3423": "Manuf",
    "3424": "Manuf",
    "3425": "Manuf",
    "3426": "Manuf",
    "3427": "Manuf",
    "3428": "Manuf",
    "3429": "Manuf",
    "3430": "Manuf",
    "3431": "Manuf",
    "3432": "Manuf",
    "3433": "Manuf",
    "3434": "Manuf",
    "3435": "Manuf",
    "3436": "Manuf",
    "3437": "Manuf",
    "3438": "Manuf",
    "3439": "Manuf",
    "3440": "Manuf",
    "3441": "Manuf",
    "3442": "Manuf",
    "3443": "Manuf",
    "3444": "Manuf",
    "3445": "Manuf",
    "3446": "Manuf",
    "3447": "Manuf",
    "3448": "Manuf",
    "3449": "Manuf",
    "3450": "Manuf",
    "3451": "Manuf",
    "3452": "Manuf",
    "3453": "Manuf",
    "3454": "Manuf",
    "3455": "Manuf",
    "3456": "Manuf",
    "3457": "Manuf",
    "3458": "Manuf",
    "3459": "Manuf",
    "3460": "Manuf",
    "3461": "Manuf",
    "3462": "Manuf",
    "3463": "Manuf",
    "3464": "Manuf",
    "3465": "Manuf",
    "3466": "Manuf",
    "3467": "Manuf",
    "3468": "Manuf",
    "3469": "Manuf",
    "3470": "Manuf",
    "3471": "Manuf",
    "3472": "Manuf",
    "3473": "Manuf",
    "3474": "Manuf",
    "3475": "Manuf",
    "3476": "Manuf",
    "3477": "Manuf",
    "3478": "Manuf",
    "3479": "Manuf",
    "3480": "Manuf",
    "3481": "Manuf",
    "3482": "Manuf",
    "3483": "Manuf",
    "3484": "Manuf",
    "3485": "Manuf",
    "3486": "Manuf",
    "3487": "Manuf",
    "3488": "Manuf",
    "3489": "Manuf",
    "3490": "Manuf",
    "3491": "Manuf",
    "3492": "Manuf",
    "3493": "Manuf",
    "3494": "Manuf",
    "3495": "Manuf",
    "3496": "Manuf",
    "3497": "Manuf",
    "3498": "Manuf",
    "3499": "Manuf",
    "3500": "Manuf",
    "3501": "Manuf",
    "3502": "Manuf",
    "3503": "Manuf",
    "3504": "Manuf",
    "3505": "Manuf",
    "3506": "Manuf",
    "3507": "Manuf",
    "3508": "Manuf",
    "3509": "Manuf",
    "3510": "Manuf",
    "3511": "Manuf",
    "3512": "Manuf",
    "3513": "Manuf",
    "3514": "Manuf",
    "3515": "Manuf",
    "3516": "Manuf",
    "3517": "Manuf",
    "3518": "Manuf",
    "3519": "Manuf",
    "3520": "Manuf",
    "3521": "Manuf",
    "3522": "Manuf",
    "3523": "Manuf",
    "3524": "Manuf",
    "3525": "Manuf",
    "3526": "Manuf",
    "3527": "Manuf",
    "3528": "Manuf",
    "3529": "Manuf",
    "3530": "Manuf",
    "3531": "Manuf",
    "3532": "Manuf",
    "3533": "Manuf",
    "3534": "Manuf",
    "3535": "Manuf",
    "3536": "Manuf",
    "3537": "Manuf",
    "3538": "Manuf",
    "3539": "Manuf",
    "3540": "Manuf",
    "3541": "Manuf",
    "3542": "Manuf",
    "3543": "Manuf",
    "3544": "Manuf",
    "3545": "Manuf",
    "3546": "Manuf",
    "3547": "Manuf",
    "3548": "Manuf",
    "3549": "Manuf",
    "3550": "Manuf",
    "3551": "Manuf",
    "3552": "Manuf",
    "3553": "Manuf",
    "3554": "Manuf",
    "3555": "Manuf",
    "3556": "Manuf",
    "3557": "Manuf",
    "3558": "Manuf",
    "3559": "Manuf",
    "3560": "Manuf",
    "3561": "Manuf",
    "3562": "Manuf",
    "3563": "Manuf",
    "3564": "Manuf",
    "3565": "Manuf",
    "3566": "Manuf",
    "3567": "Manuf",
    "3568": "Manuf",
    "3569": "Manuf",
    "3580": "Manuf",
    "3581": "Manuf",
    "3582": "Manuf",
    "3583": "Manuf",
    "3584": "Manuf",
    "3585": "Manuf",
    "3586": "Manuf",
    "3587": "Manuf",
    "3588": "Manuf",
    "3589": "Manuf",
    "3590": "Manuf",
    "3591": "Manuf",
    "3592": "Manuf",
    "3593": "Manuf",
    "3594": "Manuf",
    "3595": "Manuf",
    "3596": "Manuf",
    "3597": "Manuf",
    "3598": "Manuf",
    "3599": "Manuf",
    "3600": "Manuf",
    "3601": "Manuf",
    "3602": "Manuf",
    "3603": "Manuf",
    "3604": "Manuf",
    "3605": "Manuf",
    "3606": "Manuf",
    "3607": "Manuf",
    "3608": "Manuf",
    "3609": "Manuf",
    "3610": "Manuf",
    "3611": "Manuf",
    "3612": "Manuf",
    "3613": "Manuf",
    "3614": "Manuf",
    "3615": "Manuf",
    "3616": "Manuf",
    "3617": "Manuf",
    "3618": "Manuf",
    "3619": "Manuf",
    "3620": "Manuf",
    "3621": "Manuf",
    "3623": "Manuf",
    "3624": "Manuf",
    "3625": "Manuf",
    "3626": "Manuf",
    "3627": "Manuf",
    "3628": "Manuf",
    "3629": "Manuf",
    "3700": "Manuf",
    "3701": "Manuf",
    "3702": "Manuf",
    "3703": "Manuf",
    "3704": "Manuf",
    "3705": "Manuf",
    "3706": "Manuf",
    "3707": "Manuf",
    "3708": "Manuf",
    "3709": "Manuf",
    "3712": "Manuf",
    "3713": "Manuf",
    "3715": "Manuf",
    "3717": "Manuf",
    "3718": "Manuf",
    "3719": "Manuf",
    "3720": "Manuf",
    "3721": "Manuf",
    "3722": "Manuf",
    "3723": "Manuf",
    "3724": "Manuf",
    "3725": "Manuf",
    "3726": "Manuf",
    "3727": "Manuf",
    "3728": "Manuf",
    "3729": "Manuf",
    "3730": "Manuf",
    "3731": "Manuf",
    "3732": "Manuf",
    "3733": "Manuf",
    "3734": "Manuf",
    "3735": "Manuf",
    "3736": "Manuf",
    "3737": "Manuf",
    "3738": "Manuf",
    "3739": "Manuf",
    "3740": "Manuf",
    "3741": "Manuf",
    "3742": "Manuf",
    "3743": "Manuf",
    "3744": "Manuf",
    "3745": "Manuf",
    "3746": "Manuf",
    "3747": "Manuf",
    "3748": "Manuf",
    "3749": "Manuf",
    "3752": "Manuf",
    "3753": "Manuf",
    "3754": "Manuf",
    "3755": "Manuf",
    "3756": "Manuf",
    "3757": "Manuf",
    "3758": "Manuf",
    "3759": "Manuf",
    "3760": "Manuf",
    "3761": "Manuf",
    "3762": "Manuf",
    "3763": "Manuf",
    "3764": "Manuf",
    "3765": "Manuf",
    "3766": "Manuf",
    "3767": "Manuf",
    "3768": "Manuf",
    "3769": "Manuf",
    "3770": "Manuf",
    "3771": "Manuf",
    "3772": "Manuf",
    "3773": "Manuf",
    "3774": "Manuf",
    "3775": "Manuf",
    "3776": "Manuf",
    "3777": "Manuf",
    "3778": "Manuf",
    "3779": "Manuf",
    "3780": "Manuf",
    "3781": "Manuf",
    "3782": "Manuf",
    "3783": "Manuf",
    "3784": "Manuf",
    "3785": "Manuf",
    "3786": "Manuf",
    "3787": "Manuf",
    "3788": "Manuf",
    "3789": "Manuf",
    "3790": "Manuf",
    "3791": "Manuf",
    "3793": "Manuf",
    "3794": "Manuf",
    "3795": "Manuf",
    "3796": "Manuf",
    "3797": "Manuf",
    "3798": "Manuf",
    "3799": "Manuf",
    "3860": "Manuf",
    "3861": "Manuf",
    "3862": "Manuf",
    "3863": "Manuf",
    "3864": "Manuf",
    "3865": "Manuf",
    "3866": "Manuf",
    "3867": "Manuf",
    "3868": "Manuf",
    "3869": "Manuf",
    "3870": "Manuf",
    "3871": "Manuf",
    "3872": "Manuf",
    "3873": "Manuf",
    "3874": "Manuf",
    "3875": "Manuf",
    "3876": "Manuf",
    "3877": "Manuf",
    "3878": "Manuf",
    "3879": "Manuf",
    "3880": "Manuf",
    "3881": "Manuf",
    "3882": "Manuf",
    "3883": "Manuf",
    "3884": "Manuf",
    "3885": "Manuf",
    "3886": "Manuf",
    "3887": "Manuf",
    "3888": "Manuf",
    "3889": "Manuf",
    "3890": "Manuf",
    "3891": "Manuf",
    "3892": "Manuf",
    "3893": "Manuf",
    "3894": "Manuf",
    "3895": "Manuf",
    "3896": "Manuf",
    "3897": "Manuf",
    "3898": "Manuf",
    "3899": "Manuf",
    "1200": "Enrgy",
    "1201": "Enrgy",
    "1202": "Enrgy",
    "1203": "Enrgy",
    "1204": "Enrgy",
    "1205": "Enrgy",
    "1206": "Enrgy",
    "1207": "Enrgy",
    "1208": "Enrgy",
    "1209": "Enrgy",
    "1210": "Enrgy",
    "1211": "Enrgy",
    "1212": "Enrgy",
    "1213": "Enrgy",
    "1214": "Enrgy",
    "1215": "Enrgy",
    "1216": "Enrgy",
    "1217": "Enrgy",
    "1218": "Enrgy",
    "1219": "Enrgy",
    "1220": "Enrgy",
    "1221": "Enrgy",
    "1222": "Enrgy",
    "1223": "Enrgy",
    "1224": "Enrgy",
    "1225": "Enrgy",
    "1226": "Enrgy",
    "1227": "Enrgy",
    "1228": "Enrgy",
    "1229": "Enrgy",
    "1230": "Enrgy",
    "1231": "Enrgy",
    "1232": "Enrgy",
    "1233": "Enrgy",
    "1234": "Enrgy",
    "1235": "Enrgy",
    "1236": "Enrgy",
    "1237": "Enrgy",
    "1238": "Enrgy",
    "1239": "Enrgy",
    "1240": "Enrgy",
    "1241": "Enrgy",
    "1242": "Enrgy",
    "1243": "Enrgy",
    "1244": "Enrgy",
    "1245": "Enrgy",
    "1246": "Enrgy",
    "1247": "Enrgy",
    "1248": "Enrgy",
    "1249": "Enrgy",
    "1250": "Enrgy",
    "1251": "Enrgy",
    "1252": "Enrgy",
    "1253": "Enrgy",
    "1254": "Enrgy",
    "1255": "Enrgy",
    "1256": "Enrgy",
    "1257": "Enrgy",
    "1258": "Enrgy",
    "1259": "Enrgy",
    "1260": "Enrgy",
    "1261": "Enrgy",
    "1262": "Enrgy",
    "1263": "Enrgy",
    "1264": "Enrgy",
    "1265": "Enrgy",
    "1266": "Enrgy",
    "1267": "Enrgy",
    "1268": "Enrgy",
    "1269": "Enrgy",
    "1270": "Enrgy",
    "1271": "Enrgy",
    "1272": "Enrgy",
    "1273": "Enrgy",
    "1274": "Enrgy",
    "1275": "Enrgy",
    "1276": "Enrgy",
    "1277": "Enrgy",
    "1278": "Enrgy",
    "1279": "Enrgy",
    "1280": "Enrgy",
    "1281": "Enrgy",
    "1282": "Enrgy",
    "1283": "Enrgy",
    "1284": "Enrgy",
    "1285": "Enrgy",
    "1286": "Enrgy",
    "1287": "Enrgy",
    "1288": "Enrgy",
    "1289": "Enrgy",
    "1290": "Enrgy",
    "1291": "Enrgy",
    "1292": "Enrgy",
    "1293": "Enrgy",
    "1294": "Enrgy",
    "1295": "Enrgy",
    "1296": "Enrgy",
    "1297": "Enrgy",
    "1298": "Enrgy",
    "1299": "Enrgy",
    "1300": "Enrgy",
    "1301": "Enrgy",
    "1302": "Enrgy",
    "1303": "Enrgy",
    "1304": "Enrgy",
    "1305": "Enrgy",
    "1306": "Enrgy",
    "1307": "Enrgy",
    "1308": "Enrgy",
    "1309": "Enrgy",
    "1310": "Enrgy",
    "1311": "Enrgy",
    "1312": "Enrgy",
    "1313": "Enrgy",
    "1314": "Enrgy",
    "1315": "Enrgy",
    "1316": "Enrgy",
    "1317": "Enrgy",
    "1318": "Enrgy",
    "1319": "Enrgy",
    "1320": "Enrgy",
    "1321": "Enrgy",
    "1322": "Enrgy",
    "1323": "Enrgy",
    "1324": "Enrgy",
    "1325": "Enrgy",
    "1326": "Enrgy",
    "1327": "Enrgy",
    "1328": "Enrgy",
    "1329": "Enrgy",
    "1330": "Enrgy",
    "1331": "Enrgy",
    "1332": "Enrgy",
    "1333": "Enrgy",
    "1334": "Enrgy",
    "1335": "Enrgy",
    "1336": "Enrgy",
    "1337": "Enrgy",
    "1338": "Enrgy",
    "1339": "Enrgy",
    "1340": "Enrgy",
    "1341": "Enrgy",
    "1342": "Enrgy",
    "1343": "Enrgy",
    "1344": "Enrgy",
    "1345": "Enrgy",
    "1346": "Enrgy",
    "1347": "Enrgy",
    "1348": "Enrgy",
    "1349": "Enrgy",
    "1350": "Enrgy",
    "1351": "Enrgy",
    "1352": "Enrgy",
    "1353": "Enrgy",
    "1354": "Enrgy",
    "1355": "Enrgy",
    "1356": "Enrgy",
    "1357": "Enrgy",
    "1358": "Enrgy",
    "1359": "Enrgy",
    "1360": "Enrgy",
    "1361": "Enrgy",
    "1362": "Enrgy",
    "1363": "Enrgy",
    "1364": "Enrgy",
    "1365": "Enrgy",
    "1366": "Enrgy",
    "1367": "Enrgy",
    "1368": "Enrgy",
    "1369": "Enrgy",
    "1370": "Enrgy",
    "1371": "Enrgy",
    "1372": "Enrgy",
    "1373": "Enrgy",
    "1374": "Enrgy",
    "1375": "Enrgy",
    "1376": "Enrgy",
    "1377": "Enrgy",
    "1378": "Enrgy",
    "1379": "Enrgy",
    "1380": "Enrgy",
    "1381": "Enrgy",
    "1382": "Enrgy",
    "1383": "Enrgy",
    "1384": "Enrgy",
    "1385": "Enrgy",
    "1386": "Enrgy",
    "1387": "Enrgy",
    "1388": "Enrgy",
    "1389": "Enrgy",
    "1390": "Enrgy",
    "1391": "Enrgy",
    "1392": "Enrgy",
    "1393": "Enrgy",
    "1394": "Enrgy",
    "1395": "Enrgy",
    "1396": "Enrgy",
    "1397": "Enrgy",
    "1398": "Enrgy",
    "1399": "Enrgy",
    "2900": "Enrgy",
    "2901": "Enrgy",
    "2902": "Enrgy",
    "2903": "Enrgy",
    "2904": "Enrgy",
    "2905": "Enrgy",
    "2906": "Enrgy",
    "2907": "Enrgy",
    "2908": "Enrgy",
    "2909": "Enrgy",
    "2910": "Enrgy",
    "2911": "Enrgy",
    "2912": "Enrgy",
    "2913": "Enrgy",
    "2914": "Enrgy",
    "2915": "Enrgy",
    "2916": "Enrgy",
    "2917": "Enrgy",
    "2918": "Enrgy",
    "2919": "Enrgy",
    "2920": "Enrgy",
    "2921": "Enrgy",
    "2922": "Enrgy",
    "2923": "Enrgy",
    "2924": "Enrgy",
    "2925": "Enrgy",
    "2926": "Enrgy",
    "2927": "Enrgy",
    "2928": "Enrgy",
    "2929": "Enrgy",
    "2930": "Enrgy",
    "2931": "Enrgy",
    "2932": "Enrgy",
    "2933": "Enrgy",
    "2934": "Enrgy",
    "2935": "Enrgy",
    "2936": "Enrgy",
    "2937": "Enrgy",
    "2938": "Enrgy",
    "2939": "Enrgy",
    "2940": "Enrgy",
    "2941": "Enrgy",
    "2942": "Enrgy",
    "2943": "Enrgy",
    "2944": "Enrgy",
    "2945": "Enrgy",
    "2946": "Enrgy",
    "2947": "Enrgy",
    "2948": "Enrgy",
    "2949": "Enrgy",
    "2950": "Enrgy",
    "2951": "Enrgy",
    "2952": "Enrgy",
    "2953": "Enrgy",
    "2954": "Enrgy",
    "2955": "Enrgy",
    "2956": "Enrgy",
    "2957": "Enrgy",
    "2958": "Enrgy",
    "2959": "Enrgy",
    "2960": "Enrgy",
    "2961": "Enrgy",
    "2962": "Enrgy",
    "2963": "Enrgy",
    "2964": "Enrgy",
    "2965": "Enrgy",
    "2966": "Enrgy",
    "2967": "Enrgy",
    "2968": "Enrgy",
    "2969": "Enrgy",
    "2970": "Enrgy",
    "2971": "Enrgy",
    "2972": "Enrgy",
    "2973": "Enrgy",
    "2974": "Enrgy",
    "2975": "Enrgy",
    "2976": "Enrgy",
    "2977": "Enrgy",
    "2978": "Enrgy",
    "2979": "Enrgy",
    "2980": "Enrgy",
    "2981": "Enrgy",
    "2982": "Enrgy",
    "2983": "Enrgy",
    "2984": "Enrgy",
    "2985": "Enrgy",
    "2986": "Enrgy",
    "2987": "Enrgy",
    "2988": "Enrgy",
    "2989": "Enrgy",
    "2990": "Enrgy",
    "2991": "Enrgy",
    "2992": "Enrgy",
    "2993": "Enrgy",
    "2994": "Enrgy",
    "2995": "Enrgy",
    "2996": "Enrgy",
    "2997": "Enrgy",
    "2998": "Enrgy",
    "2999": "Enrgy",
    "3570": "HiTec",
    "3571": "HiTec",
    "3572": "HiTec",
    "3573": "HiTec",
    "3574": "HiTec",
    "3575": "HiTec",
    "3576": "HiTec",
    "3577": "HiTec",
    "3578": "HiTec",
    "3579": "HiTec",
    "3622": "HiTec",
    "3660": "HiTec",
    "3661": "HiTec",
    "3662": "HiTec",
    "3663": "HiTec",
    "3664": "HiTec",
    "3665": "HiTec",
    "3666": "HiTec",
    "3667": "HiTec",
    "3668": "HiTec",
    "3669": "HiTec",
    "3670": "HiTec",
    "3671": "HiTec",
    "3672": "HiTec",
    "3673": "HiTec",
    "3674": "HiTec",
    "3675": "HiTec",
    "3676": "HiTec",
    "3677": "HiTec",
    "3678": "HiTec",
    "3679": "HiTec",
    "3680": "HiTec",
    "3681": "HiTec",
    "3682": "HiTec",
    "3683": "HiTec",
    "3684": "HiTec",
    "3685": "HiTec",
    "3686": "HiTec",
    "3687": "HiTec",
    "3688": "HiTec",
    "3689": "HiTec",
    "3690": "HiTec",
    "3691": "HiTec",
    "3692": "HiTec",
    "3694": "HiTec",
    "3695": "HiTec",
    "3696": "HiTec",
    "3697": "HiTec",
    "3698": "HiTec",
    "3699": "HiTec",
    "3810": "HiTec",
    "3811": "HiTec",
    "3812": "HiTec",
    "3813": "HiTec",
    "3814": "HiTec",
    "3815": "HiTec",
    "3816": "HiTec",
    "3817": "HiTec",
    "3818": "HiTec",
    "3819": "HiTec",
    "3820": "HiTec",
    "3821": "HiTec",
    "3822": "HiTec",
    "3823": "HiTec",
    "3824": "HiTec",
    "3825": "HiTec",
    "3826": "HiTec",
    "3827": "HiTec",
    "3828": "HiTec",
    "3829": "HiTec",
    "3830": "HiTec",
    "3831": "HiTec",
    "3832": "HiTec",
    "3833": "HiTec",
    "3834": "HiTec",
    "3835": "HiTec",
    "3836": "HiTec",
    "3837": "HiTec",
    "3838": "HiTec",
    "3839": "HiTec",
    "7370": "HiTec",
    "7371": "HiTec",
    "7372": "HiTec",
    "7373": "HiTec",
    "7374": "HiTec",
    "7375": "HiTec",
    "7376": "HiTec",
    "7377": "HiTec",
    "7378": "HiTec",
    "7379": "HiTec",
    "7391": "HiTec",
    "8730": "HiTec",
    "8731": "HiTec",
    "8732": "HiTec",
    "8733": "HiTec",
    "8734": "HiTec",
    "4800": "Telcm",
    "4801": "Telcm",
    "4802": "Telcm",
    "4803": "Telcm",
    "4804": "Telcm",
    "4805": "Telcm",
    "4806": "Telcm",
    "4807": "Telcm",
    "4808": "Telcm",
    "4809": "Telcm",
    "4810": "Telcm",
    "4811": "Telcm",
    "4812": "Telcm",
    "4813": "Telcm",
    "4814": "Telcm",
    "4815": "Telcm",
    "4816": "Telcm",
    "4817": "Telcm",
    "4818": "Telcm",
    "4819": "Telcm",
    "4820": "Telcm",
    "4821": "Telcm",
    "4822": "Telcm",
    "4823": "Telcm",
    "4824": "Telcm",
    "4825": "Telcm",
    "4826": "Telcm",
    "4827": "Telcm",
    "4828": "Telcm",
    "4829": "Telcm",
    "4830": "Telcm",
    "4831": "Telcm",
    "4832": "Telcm",
    "4833": "Telcm",
    "4834": "Telcm",
    "4835": "Telcm",
    "4836": "Telcm",
    "4837": "Telcm",
    "4838": "Telcm",
    "4839": "Telcm",
    "4840": "Telcm",
    "4841": "Telcm",
    "4842": "Telcm",
    "4843": "Telcm",
    "4844": "Telcm",
    "4845": "Telcm",
    "4846": "Telcm",
    "4847": "Telcm",
    "4848": "Telcm",
    "4849": "Telcm",
    "4850": "Telcm",
    "4851": "Telcm",
    "4852": "Telcm",
    "4853": "Telcm",
    "4854": "Telcm",
    "4855": "Telcm",
    "4856": "Telcm",
    "4857": "Telcm",
    "4858": "Telcm",
    "4859": "Telcm",
    "4860": "Telcm",
    "4861": "Telcm",
    "4862": "Telcm",
    "4863": "Telcm",
    "4864": "Telcm",
    "4865": "Telcm",
    "4866": "Telcm",
    "4867": "Telcm",
    "4868": "Telcm",
    "4869": "Telcm",
    "4870": "Telcm",
    "4871": "Telcm",
    "4872": "Telcm",
    "4873": "Telcm",
    "4874": "Telcm",
    "4875": "Telcm",
    "4876": "Telcm",
    "4877": "Telcm",
    "4878": "Telcm",
    "4879": "Telcm",
    "4880": "Telcm",
    "4881": "Telcm",
    "4882": "Telcm",
    "4883": "Telcm",
    "4884": "Telcm",
    "4885": "Telcm",
    "4886": "Telcm",
    "4887": "Telcm",
    "4888": "Telcm",
    "4889": "Telcm",
    "4890": "Telcm",
    "4891": "Telcm",
    "4892": "Telcm",
    "4893": "Telcm",
    "4894": "Telcm",
    "4895": "Telcm",
    "4896": "Telcm",
    "4897": "Telcm",
    "4898": "Telcm",
    "4899": "Telcm",
    "5000": "Shops",
    "5001": "Shops",
    "5002": "Shops",
    "5003": "Shops",
    "5004": "Shops",
    "5005": "Shops",
    "5006": "Shops",
    "5007": "Shops",
    "5008": "Shops",
    "5009": "Shops",
    "5010": "Shops",
    "5011": "Shops",
    "5012": "Shops",
    "5013": "Shops",
    "5014": "Shops",
    "5015": "Shops",
    "5016": "Shops",
    "5017": "Shops",
    "5018": "Shops",
    "5019": "Shops",
    "5020": "Shops",
    "5021": "Shops",
    "5022": "Shops",
    "5023": "Shops",
    "5024": "Shops",
    "5025": "Shops",
    "5026": "Shops",
    "5027": "Shops",
    "5028": "Shops",
    "5029": "Shops",
    "5030": "Shops",
    "5031": "Shops",
    "5032": "Shops",
    "5033": "Shops",
    "5034": "Shops",
    "5035": "Shops",
    "5036": "Shops",
    "5037": "Shops",
    "5038": "Shops",
    "5039": "Shops",
    "5040": "Shops",
    "5041": "Shops",
    "5042": "Shops",
    "5043": "Shops",
    "5044": "Shops",
    "5045": "Shops",
    "5046": "Shops",
    "5047": "Shops",
    "5048": "Shops",
    "5049": "Shops",
    "5050": "Shops",
    "5051": "Shops",
    "5052": "Shops",
    "5053": "Shops",
    "5054": "Shops",
    "5055": "Shops",
    "5056": "Shops",
    "5057": "Shops",
    "5058": "Shops",
    "5059": "Shops",
    "5060": "Shops",
    "5061": "Shops",
    "5062": "Shops",
    "5063": "Shops",
    "5064": "Shops",
    "5065": "Shops",
    "5066": "Shops",
    "5067": "Shops",
    "5068": "Shops",
    "5069": "Shops",
    "5070": "Shops",
    "5071": "Shops",
    "5072": "Shops",
    "5073": "Shops",
    "5074": "Shops",
    "5075": "Shops",
    "5076": "Shops",
    "5077": "Shops",
    "5078": "Shops",
    "5079": "Shops",
    "5080": "Shops",
    "5081": "Shops",
    "5082": "Shops",
    "5083": "Shops",
    "5084": "Shops",
    "5085": "Shops",
    "5086": "Shops",
    "5087": "Shops",
    "5088": "Shops",
    "5089": "Shops",
    "5090": "Shops",
    "5091": "Shops",
    "5092": "Shops",
    "5093": "Shops",
    "5094": "Shops",
    "5095": "Shops",
    "5096": "Shops",
    "5097": "Shops",
    "5098": "Shops",
    "5099": "Shops",
    "5100": "Shops",
    "5101": "Shops",
    "5102": "Shops",
    "5103": "Shops",
    "5104": "Shops",
    "5105": "Shops",
    "5106": "Shops",
    "5107": "Shops",
    "5108": "Shops",
    "5109": "Shops",
    "5110": "Shops",
    "5111": "Shops",
    "5112": "Shops",
    "5113": "Shops",
    "5114": "Shops",
    "5115": "Shops",
    "5116": "Shops",
    "5117": "Shops",
    "5118": "Shops",
    "5119": "Shops",
    "5120": "Shops",
    "5121": "Shops",
    "5122": "Shops",
    "5123": "Shops",
    "5124": "Shops",
    "5125": "Shops",
    "5126": "Shops",
    "5127": "Shops",
    "5128": "Shops",
    "5129": "Shops",
    "5130": "Shops",
    "5131": "Shops",
    "5132": "Shops",
    "5133": "Shops",
    "5134": "Shops",
    "5135": "Shops",
    "5136": "Shops",
    "5137": "Shops",
    "5138": "Shops",
    "5139": "Shops",
    "5140": "Shops",
    "5141": "Shops",
    "5142": "Shops",
    "5143": "Shops",
    "5144": "Shops",
    "5145": "Shops",
    "5146": "Shops",
    "5147": "Shops",
    "5148": "Shops",
    "5149": "Shops",
    "5150": "Shops",
    "5151": "Shops",
    "5152": "Shops",
    "5153": "Shops",
    "5154": "Shops",
    "5155": "Shops",
    "5156": "Shops",
    "5157": "Shops",
    "5158": "Shops",
    "5159": "Shops",
    "5160": "Shops",
    "5161": "Shops",
    "5162": "Shops",
    "5163": "Shops",
    "5164": "Shops",
    "5165": "Shops",
    "5166": "Shops",
    "5167": "Shops",
    "5168": "Shops",
    "5169": "Shops",
    "5170": "Shops",
    "5171": "Shops",
    "5172": "Shops",
    "5173": "Shops",
    "5174": "Shops",
    "5175": "Shops",
    "5176": "Shops",
    "5177": "Shops",
    "5178": "Shops",
    "5179": "Shops",
    "5180": "Shops",
    "5181": "Shops",
    "5182": "Shops",
    "5183": "Shops",
    "5184": "Shops",
    "5185": "Shops",
    "5186": "Shops",
    "5187": "Shops",
    "5188": "Shops",
    "5189": "Shops",
    "5190": "Shops",
    "5191": "Shops",
    "5192": "Shops",
    "5193": "Shops",
    "5194": "Shops",
    "5195": "Shops",
    "5196": "Shops",
    "5197": "Shops",
    "5198": "Shops",
    "5199": "Shops",
    "5200": "Shops",
    "5201": "Shops",
    "5202": "Shops",
    "5203": "Shops",
    "5204": "Shops",
    "5205": "Shops",
    "5206": "Shops",
    "5207": "Shops",
    "5208": "Shops",
    "5209": "Shops",
    "5210": "Shops",
    "5211": "Shops",
    "5212": "Shops",
    "5213": "Shops",
    "5214": "Shops",
    "5215": "Shops",
    "5216": "Shops",
    "5217": "Shops",
    "5218": "Shops",
    "5219": "Shops",
    "5220": "Shops",
    "5221": "Shops",
    "5222": "Shops",
    "5223": "Shops",
    "5224": "Shops",
    "5225": "Shops",
    "5226": "Shops",
    "5227": "Shops",
    "5228": "Shops",
    "5229": "Shops",
    "5230": "Shops",
    "5231": "Shops",
    "5232": "Shops",
    "5233": "Shops",
    "5234": "Shops",
    "5235": "Shops",
    "5236": "Shops",
    "5237": "Shops",
    "5238": "Shops",
    "5239": "Shops",
    "5240": "Shops",
    "5241": "Shops",
    "5242": "Shops",
    "5243": "Shops",
    "5244": "Shops",
    "5245": "Shops",
    "5246": "Shops",
    "5247": "Shops",
    "5248": "Shops",
    "5249": "Shops",
    "5250": "Shops",
    "5251": "Shops",
    "5252": "Shops",
    "5253": "Shops",
    "5254": "Shops",
    "5255": "Shops",
    "5256": "Shops",
    "5257": "Shops",
    "5258": "Shops",
    "5259": "Shops",
    "5260": "Shops",
    "5261": "Shops",
    "5262": "Shops",
    "5263": "Shops",
    "5264": "Shops",
    "5265": "Shops",
    "5266": "Shops",
    "5267": "Shops",
    "5268": "Shops",
    "5269": "Shops",
    "5270": "Shops",
    "5271": "Shops",
    "5272": "Shops",
    "5273": "Shops",
    "5274": "Shops",
    "5275": "Shops",
    "5276": "Shops",
    "5277": "Shops",
    "5278": "Shops",
    "5279": "Shops",
    "5280": "Shops",
    "5281": "Shops",
    "5282": "Shops",
    "5283": "Shops",
    "5284": "Shops",
    "5285": "Shops",
    "5286": "Shops",
    "5287": "Shops",
    "5288": "Shops",
    "5289": "Shops",
    "5290": "Shops",
    "5291": "Shops",
    "5292": "Shops",
    "5293": "Shops",
    "5294": "Shops",
    "5295": "Shops",
    "5296": "Shops",
    "5297": "Shops",
    "5298": "Shops",
    "5299": "Shops",
    "5300": "Shops",
    "5301": "Shops",
    "5302": "Shops",
    "5303": "Shops",
    "5304": "Shops",
    "5305": "Shops",
    "5306": "Shops",
    "5307": "Shops",
    "5308": "Shops",
    "5309": "Shops",
    "5310": "Shops",
    "5311": "Shops",
    "5312": "Shops",
    "5313": "Shops",
    "5314": "Shops",
    "5315": "Shops",
    "5316": "Shops",
    "5317": "Shops",
    "5318": "Shops",
    "5319": "Shops",
    "5320": "Shops",
    "5321": "Shops",
    "5322": "Shops",
    "5323": "Shops",
    "5324": "Shops",
    "5325": "Shops",
    "5326": "Shops",
    "5327": "Shops",
    "5328": "Shops",
    "5329": "Shops",
    "5330": "Shops",
    "5331": "Shops",
    "5332": "Shops",
    "5333": "Shops",
    "5334": "Shops",
    "5335": "Shops",
    "5336": "Shops",
    "5337": "Shops",
    "5338": "Shops",
    "5339": "Shops",
    "5340": "Shops",
    "5341": "Shops",
    "5342": "Shops",
    "5343": "Shops",
    "5344": "Shops",
    "5345": "Shops",
    "5346": "Shops",
    "5347": "Shops",
    "5348": "Shops",
    "5349": "Shops",
    "5350": "Shops",
    "5351": "Shops",
    "5352": "Shops",
    "5353": "Shops",
    "5354": "Shops",
    "5355": "Shops",
    "5356": "Shops",
    "5357": "Shops",
    "5358": "Shops",
    "5359": "Shops",
    "5360": "Shops",
    "5361": "Shops",
    "5362": "Shops",
    "5363": "Shops",
    "5364": "Shops",
    "5365": "Shops",
    "5366": "Shops",
    "5367": "Shops",
    "5368": "Shops",
    "5369": "Shops",
    "5370": "Shops",
    "5371": "Shops",
    "5372": "Shops",
    "5373": "Shops",
    "5374": "Shops",
    "5375": "Shops",
    "5376": "Shops",
    "5377": "Shops",
    "5378": "Shops",
    "5379": "Shops",
    "5380": "Shops",
    "5381": "Shops",
    "5382": "Shops",
    "5383": "Shops",
    "5384": "Shops",
    "5385": "Shops",
    "5386": "Shops",
    "5387": "Shops",
    "5388": "Shops",
    "5389": "Shops",
    "5390": "Shops",
    "5391": "Shops",
    "5392": "Shops",
    "5393": "Shops",
    "5394": "Shops",
    "5395": "Shops",
    "5396": "Shops",
    "5397": "Shops",
    "5398": "Shops",
    "5399": "Shops",
    "5400": "Shops",
    "5401": "Shops",
    "5402": "Shops",
    "5403": "Shops",
    "5404": "Shops",
    "5405": "Shops",
    "5406": "Shops",
    "5407": "Shops",
    "5408": "Shops",
    "5409": "Shops",
    "5410": "Shops",
    "5411": "Shops",
    "5412": "Shops",
    "5413": "Shops",
    "5414": "Shops",
    "5415": "Shops",
    "5416": "Shops",
    "5417": "Shops",
    "5418": "Shops",
    "5419": "Shops",
    "5420": "Shops",
    "5421": "Shops",
    "5422": "Shops",
    "5423": "Shops",
    "5424": "Shops",
    "5425": "Shops",
    "5426": "Shops",
    "5427": "Shops",
    "5428": "Shops",
    "5429": "Shops",
    "5430": "Shops",
    "5431": "Shops",
    "5432": "Shops",
    "5433": "Shops",
    "5434": "Shops",
    "5435": "Shops",
    "5436": "Shops",
    "5437": "Shops",
    "5438": "Shops",
    "5439": "Shops",
    "5440": "Shops",
    "5441": "Shops",
    "5442": "Shops",
    "5443": "Shops",
    "5444": "Shops",
    "5445": "Shops",
    "5446": "Shops",
    "5447": "Shops",
    "5448": "Shops",
    "5449": "Shops",
    "5450": "Shops",
    "5451": "Shops",
    "5452": "Shops",
    "5453": "Shops",
    "5454": "Shops",
    "5455": "Shops",
    "5456": "Shops",
    "5457": "Shops",
    "5458": "Shops",
    "5459": "Shops",
    "5460": "Shops",
    "5461": "Shops",
    "5462": "Shops",
    "5463": "Shops",
    "5464": "Shops",
    "5465": "Shops",
    "5466": "Shops",
    "5467": "Shops",
    "5468": "Shops",
    "5469": "Shops",
    "5470": "Shops",
    "5471": "Shops",
    "5472": "Shops",
    "5473": "Shops",
    "5474": "Shops",
    "5475": "Shops",
    "5476": "Shops",
    "5477": "Shops",
    "5478": "Shops",
    "5479": "Shops",
    "5480": "Shops",
    "5481": "Shops",
    "5482": "Shops",
    "5483": "Shops",
    "5484": "Shops",
    "5485": "Shops",
    "5486": "Shops",
    "5487": "Shops",
    "5488": "Shops",
    "5489": "Shops",
    "5490": "Shops",
    "5491": "Shops",
    "5492": "Shops",
    "5493": "Shops",
    "5494": "Shops",
    "5495": "Shops",
    "5496": "Shops",
    "5497": "Shops",
    "5498": "Shops",
    "5499": "Shops",
    "5500": "Shops",
    "5501": "Shops",
    "5502": "Shops",
    "5503": "Shops",
    "5504": "Shops",
    "5505": "Shops",
    "5506": "Shops",
    "5507": "Shops",
    "5508": "Shops",
    "5509": "Shops",
    "5510": "Shops",
    "5511": "Shops",
    "5512": "Shops",
    "5513": "Shops",
    "5514": "Shops",
    "5515": "Shops",
    "5516": "Shops",
    "5517": "Shops",
    "5518": "Shops",
    "5519": "Shops",
    "5520": "Shops",
    "5521": "Shops",
    "5522": "Shops",
    "5523": "Shops",
    "5524": "Shops",
    "5525": "Shops",
    "5526": "Shops",
    "5527": "Shops",
    "5528": "Shops",
    "5529": "Shops",
    "5530": "Shops",
    "5531": "Shops",
    "5532": "Shops",
    "5533": "Shops",
    "5534": "Shops",
    "5535": "Shops",
    "5536": "Shops",
    "5537": "Shops",
    "5538": "Shops",
    "5539": "Shops",
    "5540": "Shops",
    "5541": "Shops",
    "5542": "Shops",
    "5543": "Shops",
    "5544": "Shops",
    "5545": "Shops",
    "5546": "Shops",
    "5547": "Shops",
    "5548": "Shops",
    "5549": "Shops",
    "5550": "Shops",
    "5551": "Shops",
    "5552": "Shops",
    "5553": "Shops",
    "5554": "Shops",
    "5555": "Shops",
    "5556": "Shops",
    "5557": "Shops",
    "5558": "Shops",
    "5559": "Shops",
    "5560": "Shops",
    "5561": "Shops",
    "5562": "Shops",
    "5563": "Shops",
    "5564": "Shops",
    "5565": "Shops",
    "5566": "Shops",
    "5567": "Shops",
    "5568": "Shops",
    "5569": "Shops",
    "5570": "Shops",
    "5571": "Shops",
    "5572": "Shops",
    "5573": "Shops",
    "5574": "Shops",
    "5575": "Shops",
    "5576": "Shops",
    "5577": "Shops",
    "5578": "Shops",
    "5579": "Shops",
    "5580": "Shops",
    "5581": "Shops",
    "5582": "Shops",
    "5583": "Shops",
    "5584": "Shops",
    "5585": "Shops",
    "5586": "Shops",
    "5587": "Shops",
    "5588": "Shops",
    "5589": "Shops",
    "5590": "Shops",
    "5591": "Shops",
    "5592": "Shops",
    "5593": "Shops",
    "5594": "Shops",
    "5595": "Shops",
    "5596": "Shops",
    "5597": "Shops",
    "5598": "Shops",
    "5599": "Shops",
    "5600": "Shops",
    "5601": "Shops",
    "5602": "Shops",
    "5603": "Shops",
    "5604": "Shops",
    "5605": "Shops",
    "5606": "Shops",
    "5607": "Shops",
    "5608": "Shops",
    "5609": "Shops",
    "5610": "Shops",
    "5611": "Shops",
    "5612": "Shops",
    "5613": "Shops",
    "5614": "Shops",
    "5615": "Shops",
    "5616": "Shops",
    "5617": "Shops",
    "5618": "Shops",
    "5619": "Shops",
    "5620": "Shops",
    "5621": "Shops",
    "5622": "Shops",
    "5623": "Shops",
    "5624": "Shops",
    "5625": "Shops",
    "5626": "Shops",
    "5627": "Shops",
    "5628": "Shops",
    "5629": "Shops",
    "5630": "Shops",
    "5631": "Shops",
    "5632": "Shops",
    "5633": "Shops",
    "5634": "Shops",
    "5635": "Shops",
    "5636": "Shops",
    "5637": "Shops",
    "5638": "Shops",
    "5639": "Shops",
    "5640": "Shops",
    "5641": "Shops",
    "5642": "Shops",
    "5643": "Shops",
    "5644": "Shops",
    "5645": "Shops",
    "5646": "Shops",
    "5647": "Shops",
    "5648": "Shops",
    "5649": "Shops",
    "5650": "Shops",
    "5651": "Shops",
    "5652": "Shops",
    "5653": "Shops",
    "5654": "Shops",
    "5655": "Shops",
    "5656": "Shops",
    "5657": "Shops",
    "5658": "Shops",
    "5659": "Shops",
    "5660": "Shops",
    "5661": "Shops",
    "5662": "Shops",
    "5663": "Shops",
    "5664": "Shops",
    "5665": "Shops",
    "5666": "Shops",
    "5667": "Shops",
    "5668": "Shops",
    "5669": "Shops",
    "5670": "Shops",
    "5671": "Shops",
    "5672": "Shops",
    "5673": "Shops",
    "5674": "Shops",
    "5675": "Shops",
    "5676": "Shops",
    "5677": "Shops",
    "5678": "Shops",
    "5679": "Shops",
    "5680": "Shops",
    "5681": "Shops",
    "5682": "Shops",
    "5683": "Shops",
    "5684": "Shops",
    "5685": "Shops",
    "5686": "Shops",
    "5687": "Shops",
    "5688": "Shops",
    "5689": "Shops",
    "5690": "Shops",
    "5691": "Shops",
    "5692": "Shops",
    "5693": "Shops",
    "5694": "Shops",
    "5695": "Shops",
    "5696": "Shops",
    "5697": "Shops",
    "5698": "Shops",
    "5699": "Shops",
    "5700": "Shops",
    "5701": "Shops",
    "5702": "Shops",
    "5703": "Shops",
    "5704": "Shops",
    "5705": "Shops",
    "5706": "Shops",
    "5707": "Shops",
    "5708": "Shops",
    "5709": "Shops",
    "5710": "Shops",
    "5711": "Shops",
    "5712": "Shops",
    "5713": "Shops",
    "5714": "Shops",
    "5715": "Shops",
    "5716": "Shops",
    "5717": "Shops",
    "5718": "Shops",
    "5719": "Shops",
    "5720": "Shops",
    "5721": "Shops",
    "5722": "Shops",
    "5723": "Shops",
    "5724": "Shops",
    "5725": "Shops",
    "5726": "Shops",
    "5727": "Shops",
    "5728": "Shops",
    "5729": "Shops",
    "5730": "Shops",
    "5731": "Shops",
    "5732": "Shops",
    "5733": "Shops",
    "5734": "Shops",
    "5735": "Shops",
    "5736": "Shops",
    "5737": "Shops",
    "5738": "Shops",
    "5739": "Shops",
    "5740": "Shops",
    "5741": "Shops",
    "5742": "Shops",
    "5743": "Shops",
    "5744": "Shops",
    "5745": "Shops",
    "5746": "Shops",
    "5747": "Shops",
    "5748": "Shops",
    "5749": "Shops",
    "5750": "Shops",
    "5751": "Shops",
    "5752": "Shops",
    "5753": "Shops",
    "5754": "Shops",
    "5755": "Shops",
    "5756": "Shops",
    "5757": "Shops",
    "5758": "Shops",
    "5759": "Shops",
    "5760": "Shops",
    "5761": "Shops",
    "5762": "Shops",
    "5763": "Shops",
    "5764": "Shops",
    "5765": "Shops",
    "5766": "Shops",
    "5767": "Shops",
    "5768": "Shops",
    "5769": "Shops",
    "5770": "Shops",
    "5771": "Shops",
    "5772": "Shops",
    "5773": "Shops",
    "5774": "Shops",
    "5775": "Shops",
    "5776": "Shops",
    "5777": "Shops",
    "5778": "Shops",
    "5779": "Shops",
    "5780": "Shops",
    "5781": "Shops",
    "5782": "Shops",
    "5783": "Shops",
    "5784": "Shops",
    "5785": "Shops",
    "5786": "Shops",
    "5787": "Shops",
    "5788": "Shops",
    "5789": "Shops",
    "5790": "Shops",
    "5791": "Shops",
    "5792": "Shops",
    "5793": "Shops",
    "5794": "Shops",
    "5795": "Shops",
    "5796": "Shops",
    "5797": "Shops",
    "5798": "Shops",
    "5799": "Shops",
    "5800": "Shops",
    "5801": "Shops",
    "5802": "Shops",
    "5803": "Shops",
    "5804": "Shops",
    "5805": "Shops",
    "5806": "Shops",
    "5807": "Shops",
    "5808": "Shops",
    "5809": "Shops",
    "5810": "Shops",
    "5811": "Shops",
    "5812": "Shops",
    "5813": "Shops",
    "5814": "Shops",
    "5815": "Shops",
    "5816": "Shops",
    "5817": "Shops",
    "5818": "Shops",
    "5819": "Shops",
    "5820": "Shops",
    "5821": "Shops",
    "5822": "Shops",
    "5823": "Shops",
    "5824": "Shops",
    "5825": "Shops",
    "5826": "Shops",
    "5827": "Shops",
    "5828": "Shops",
    "5829": "Shops",
    "5830": "Shops",
    "5831": "Shops",
    "5832": "Shops",
    "5833": "Shops",
    "5834": "Shops",
    "5835": "Shops",
    "5836": "Shops",
    "5837": "Shops",
    "5838": "Shops",
    "5839": "Shops",
    "5840": "Shops",
    "5841": "Shops",
    "5842": "Shops",
    "5843": "Shops",
    "5844": "Shops",
    "5845": "Shops",
    "5846": "Shops",
    "5847": "Shops",
    "5848": "Shops",
    "5849": "Shops",
    "5850": "Shops",
    "5851": "Shops",
    "5852": "Shops",
    "5853": "Shops",
    "5854": "Shops",
    "5855": "Shops",
    "5856": "Shops",
    "5857": "Shops",
    "5858": "Shops",
    "5859": "Shops",
    "5860": "Shops",
    "5861": "Shops",
    "5862": "Shops",
    "5863": "Shops",
    "5864": "Shops",
    "5865": "Shops",
    "5866": "Shops",
    "5867": "Shops",
    "5868": "Shops",
    "5869": "Shops",
    "5870": "Shops",
    "5871": "Shops",
    "5872": "Shops",
    "5873": "Shops",
    "5874": "Shops",
    "5875": "Shops",
    "5876": "Shops",
    "5877": "Shops",
    "5878": "Shops",
    "5879": "Shops",
    "5880": "Shops",
    "5881": "Shops",
    "5882": "Shops",
    "5883": "Shops",
    "5884": "Shops",
    "5885": "Shops",
    "5886": "Shops",
    "5887": "Shops",
    "5888": "Shops",
    "5889": "Shops",
    "5890": "Shops",
    "5891": "Shops",
    "5892": "Shops",
    "5893": "Shops",
    "5894": "Shops",
    "5895": "Shops",
    "5896": "Shops",
    "5897": "Shops",
    "5898": "Shops",
    "5899": "Shops",
    "5900": "Shops",
    "5901": "Shops",
    "5902": "Shops",
    "5903": "Shops",
    "5904": "Shops",
    "5905": "Shops",
    "5906": "Shops",
    "5907": "Shops",
    "5908": "Shops",
    "5909": "Shops",
    "5910": "Shops",
    "5911": "Shops",
    "5912": "Shops",
    "5913": "Shops",
    "5914": "Shops",
    "5915": "Shops",
    "5916": "Shops",
    "5917": "Shops",
    "5918": "Shops",
    "5919": "Shops",
    "5920": "Shops",
    "5921": "Shops",
    "5922": "Shops",
    "5923": "Shops",
    "5924": "Shops",
    "5925": "Shops",
    "5926": "Shops",
    "5927": "Shops",
    "5928": "Shops",
    "5929": "Shops",
    "5930": "Shops",
    "5931": "Shops",
    "5932": "Shops",
    "5933": "Shops",
    "5934": "Shops",
    "5935": "Shops",
    "5936": "Shops",
    "5937": "Shops",
    "5938": "Shops",
    "5939": "Shops",
    "5940": "Shops",
    "5941": "Shops",
    "5942": "Shops",
    "5943": "Shops",
    "5944": "Shops",
    "5945": "Shops",
    "5946": "Shops",
    "5947": "Shops",
    "5948": "Shops",
    "5949": "Shops",
    "5950": "Shops",
    "5951": "Shops",
    "5952": "Shops",
    "5953": "Shops",
    "5954": "Shops",
    "5955": "Shops",
    "5956": "Shops",
    "5957": "Shops",
    "5958": "Shops",
    "5959": "Shops",
    "5960": "Shops",
    "5961": "Shops",
    "5962": "Shops",
    "5963": "Shops",
    "5964": "Shops",
    "5965": "Shops",
    "5966": "Shops",
    "5967": "Shops",
    "5968": "Shops",
    "5969": "Shops",
    "5970": "Shops",
    "5971": "Shops",
    "5972": "Shops",
    "5973": "Shops",
    "5974": "Shops",
    "5975": "Shops",
    "5976": "Shops",
    "5977": "Shops",
    "5978": "Shops",
    "5979": "Shops",
    "5980": "Shops",
    "5981": "Shops",
    "5982": "Shops",
    "5983": "Shops",
    "5984": "Shops",
    "5985": "Shops",
    "5986": "Shops",
    "5987": "Shops",
    "5988": "Shops",
    "5989": "Shops",
    "5990": "Shops",
    "5991": "Shops",
    "5992": "Shops",
    "5993": "Shops",
    "5994": "Shops",
    "5995": "Shops",
    "5996": "Shops",
    "5997": "Shops",
    "5998": "Shops",
    "5999": "Shops",
    "7200": "Shops",
    "7201": "Shops",
    "7202": "Shops",
    "7203": "Shops",
    "7204": "Shops",
    "7205": "Shops",
    "7206": "Shops",
    "7207": "Shops",
    "7208": "Shops",
    "7209": "Shops",
    "7210": "Shops",
    "7211": "Shops",
    "7212": "Shops",
    "7213": "Shops",
    "7214": "Shops",
    "7215": "Shops",
    "7216": "Shops",
    "7217": "Shops",
    "7218": "Shops",
    "7219": "Shops",
    "7220": "Shops",
    "7221": "Shops",
    "7222": "Shops",
    "7223": "Shops",
    "7224": "Shops",
    "7225": "Shops",
    "7226": "Shops",
    "7227": "Shops",
    "7228": "Shops",
    "7229": "Shops",
    "7230": "Shops",
    "7231": "Shops",
    "7232": "Shops",
    "7233": "Shops",
    "7234": "Shops",
    "7235": "Shops",
    "7236": "Shops",
    "7237": "Shops",
    "7238": "Shops",
    "7239": "Shops",
    "7240": "Shops",
    "7241": "Shops",
    "7242": "Shops",
    "7243": "Shops",
    "7244": "Shops",
    "7245": "Shops",
    "7246": "Shops",
    "7247": "Shops",
    "7248": "Shops",
    "7249": "Shops",
    "7250": "Shops",
    "7251": "Shops",
    "7252": "Shops",
    "7253": "Shops",
    "7254": "Shops",
    "7255": "Shops",
    "7256": "Shops",
    "7257": "Shops",
    "7258": "Shops",
    "7259": "Shops",
    "7260": "Shops",
    "7261": "Shops",
    "7262": "Shops",
    "7263": "Shops",
    "7264": "Shops",
    "7265": "Shops",
    "7266": "Shops",
    "7267": "Shops",
    "7268": "Shops",
    "7269": "Shops",
    "7270": "Shops",
    "7271": "Shops",
    "7272": "Shops",
    "7273": "Shops",
    "7274": "Shops",
    "7275": "Shops",
    "7276": "Shops",
    "7277": "Shops",
    "7278": "Shops",
    "7279": "Shops",
    "7280": "Shops",
    "7281": "Shops",
    "7282": "Shops",
    "7283": "Shops",
    "7284": "Shops",
    "7285": "Shops",
    "7286": "Shops",
    "7287": "Shops",
    "7288": "Shops",
    "7289": "Shops",
    "7290": "Shops",
    "7291": "Shops",
    "7292": "Shops",
    "7293": "Shops",
    "7294": "Shops",
    "7295": "Shops",
    "7296": "Shops",
    "7297": "Shops",
    "7298": "Shops",
    "7299": "Shops",
    "7600": "Shops",
    "7601": "Shops",
    "7602": "Shops",
    "7603": "Shops",
    "7604": "Shops",
    "7605": "Shops",
    "7606": "Shops",
    "7607": "Shops",
    "7608": "Shops",
    "7609": "Shops",
    "7610": "Shops",
    "7611": "Shops",
    "7612": "Shops",
    "7613": "Shops",
    "7614": "Shops",
    "7615": "Shops",
    "7616": "Shops",
    "7617": "Shops",
    "7618": "Shops",
    "7619": "Shops",
    "7620": "Shops",
    "7621": "Shops",
    "7622": "Shops",
    "7623": "Shops",
    "7624": "Shops",
    "7625": "Shops",
    "7626": "Shops",
    "7627": "Shops",
    "7628": "Shops",
    "7629": "Shops",
    "7630": "Shops",
    "7631": "Shops",
    "7632": "Shops",
    "7633": "Shops",
    "7634": "Shops",
    "7635": "Shops",
    "7636": "Shops",
    "7637": "Shops",
    "7638": "Shops",
    "7639": "Shops",
    "7640": "Shops",
    "7641": "Shops",
    "7642": "Shops",
    "7643": "Shops",
    "7644": "Shops",
    "7645": "Shops",
    "7646": "Shops",
    "7647": "Shops",
    "7648": "Shops",
    "7649": "Shops",
    "7650": "Shops",
    "7651": "Shops",
    "7652": "Shops",
    "7653": "Shops",
    "7654": "Shops",
    "7655": "Shops",
    "7656": "Shops",
    "7657": "Shops",
    "7658": "Shops",
    "7659": "Shops",
    "7660": "Shops",
    "7661": "Shops",
    "7662": "Shops",
    "7663": "Shops",
    "7664": "Shops",
    "7665": "Shops",
    "7666": "Shops",
    "7667": "Shops",
    "7668": "Shops",
    "7669": "Shops",
    "7670": "Shops",
    "7671": "Shops",
    "7672": "Shops",
    "7673": "Shops",
    "7674": "Shops",
    "7675": "Shops",
    "7676": "Shops",
    "7677": "Shops",
    "7678": "Shops",
    "7679": "Shops",
    "7680": "Shops",
    "7681": "Shops",
    "7682": "Shops",
    "7683": "Shops",
    "7684": "Shops",
    "7685": "Shops",
    "7686": "Shops",
    "7687": "Shops",
    "7688": "Shops",
    "7689": "Shops",
    "7690": "Shops",
    "7691": "Shops",
    "7692": "Shops",
    "7693": "Shops",
    "7694": "Shops",
    "7695": "Shops",
    "7696": "Shops",
    "7697": "Shops",
    "7698": "Shops",
    "7699": "Shops",
    "2830": "Hlth",
    "2831": "Hlth",
    "2832": "Hlth",
    "2833": "Hlth",
    "2834": "Hlth",
    "2835": "Hlth",
    "2836": "Hlth",
    "2837": "Hlth",
    "2838": "Hlth",
    "2839": "Hlth",
    "3693": "Hlth",
    "3840": "Hlth",
    "3841": "Hlth",
    "3842": "Hlth",
    "3843": "Hlth",
    "3844": "Hlth",
    "3845": "Hlth",
    "3846": "Hlth",
    "3847": "Hlth",
    "3848": "Hlth",
    "3849": "Hlth",
    "3850": "Hlth",
    "3851": "Hlth",
    "3852": "Hlth",
    "3853": "Hlth",
    "3854": "Hlth",
    "3855": "Hlth",
    "3856": "Hlth",
    "3857": "Hlth",
    "3858": "Hlth",
    "3859": "Hlth",
    "8000": "Hlth",
    "8001": "Hlth",
    "8002": "Hlth",
    "8003": "Hlth",
    "8004": "Hlth",
    "8005": "Hlth",
    "8006": "Hlth",
    "8007": "Hlth",
    "8008": "Hlth",
    "8009": "Hlth",
    "8010": "Hlth",
    "8011": "Hlth",
    "8012": "Hlth",
    "8013": "Hlth",
    "8014": "Hlth",
    "8015": "Hlth",
    "8016": "Hlth",
    "8017": "Hlth",
    "8018": "Hlth",
    "8019": "Hlth",
    "8020": "Hlth",
    "8021": "Hlth",
    "8022": "Hlth",
    "8023": "Hlth",
    "8024": "Hlth",
    "8025": "Hlth",
    "8026": "Hlth",
    "8027": "Hlth",
    "8028": "Hlth",
    "8029": "Hlth",
    "8030": "Hlth",
    "8031": "Hlth",
    "8032": "Hlth",
    "8033": "Hlth",
    "8034": "Hlth",
    "8035": "Hlth",
    "8036": "Hlth",
    "8037": "Hlth",
    "8038": "Hlth",
    "8039": "Hlth",
    "8040": "Hlth",
    "8041": "Hlth",
    "8042": "Hlth",
    "8043": "Hlth",
    "8044": "Hlth",
    "8045": "Hlth",
    "8046": "Hlth",
    "8047": "Hlth",
    "8048": "Hlth",
    "8049": "Hlth",
    "8050": "Hlth",
    "8051": "Hlth",
    "8052": "Hlth",
    "8053": "Hlth",
    "8054": "Hlth",
    "8055": "Hlth",
    "8056": "Hlth",
    "8057": "Hlth",
    "8058": "Hlth",
    "8059": "Hlth",
    "8060": "Hlth",
    "8061": "Hlth",
    "8062": "Hlth",
    "8063": "Hlth",
    "8064": "Hlth",
    "8065": "Hlth",
    "8066": "Hlth",
    "8067": "Hlth",
    "8068": "Hlth",
    "8069": "Hlth",
    "8070": "Hlth",
    "8071": "Hlth",
    "8072": "Hlth",
    "8073": "Hlth",
    "8074": "Hlth",
    "8075": "Hlth",
    "8076": "Hlth",
    "8077": "Hlth",
    "8078": "Hlth",
    "8079": "Hlth",
    "8080": "Hlth",
    "8081": "Hlth",
    "8082": "Hlth",
    "8083": "Hlth",
    "8084": "Hlth",
    "8085": "Hlth",
    "8086": "Hlth",
    "8087": "Hlth",
    "8088": "Hlth",
    "8089": "Hlth",
    "8090": "Hlth",
    "8091": "Hlth",
    "8092": "Hlth",
    "8093": "Hlth",
    "8094": "Hlth",
    "8095": "Hlth",
    "8096": "Hlth",
    "8097": "Hlth",
    "8098": "Hlth",
    "8099": "Hlth",
    "4900": "Utils",
    "4901": "Utils",
    "4902": "Utils",
    "4903": "Utils",
    "4904": "Utils",
    "4905": "Utils",
    "4906": "Utils",
    "4907": "Utils",
    "4908": "Utils",
    "4909": "Utils",
    "4910": "Utils",
    "4911": "Utils",
    "4912": "Utils",
    "4913": "Utils",
    "4914": "Utils",
    "4915": "Utils",
    "4916": "Utils",
    "4917": "Utils",
    "4918": "Utils",
    "4919": "Utils",
    "4920": "Utils",
    "4921": "Utils",
    "4922": "Utils",
    "4923": "Utils",
    "4924": "Utils",
    "4925": "Utils",
    "4926": "Utils",
    "4927": "Utils",
    "4928": "Utils",
    "4929": "Utils",
    "4930": "Utils",
    "4931": "Utils",
    "4932": "Utils",
    "4933": "Utils",
    "4934": "Utils",
    "4935": "Utils",
    "4936": "Utils",
    "4937": "Utils",
    "4938": "Utils",
    "4939": "Utils",
    "4940": "Utils",
    "4941": "Utils",
    "4942": "Utils",
    "4943": "Utils",
    "4944": "Utils",
    "4945": "Utils",
    "4946": "Utils",
    "4947": "Utils",
    "4948": "Utils",
    "4949": "Utils"
}